{
  "File: Charge_Summary_Data_sidis_epip_richcap.inb.qa.new8.nSidis_005032.hipo.json": {
    "input_file": "nSidis_005032.hipo",
    "output_root": "Data_sidis_epip_richcap.inb.qa.new8.nSidis_005032.hipo.root",
    "accumulated_charge": 0.0,
    "total_events": 0,
    "events_after_PID_Cuts": 0,
    "Pass_1_PID_Cut_events": 0,
    "Multiple_Pions_Per_event": 0,
    "RunTime_in_secs": 24,
    "timestamp": "2026-04-15T22:16:18.590140153Z"
  },
  "File: Charge_Summary_Data_sidis_epip_richcap.inb.qa.new8.nSidis_005036.hipo.json": {
    "input_file": "nSidis_005036.hipo",
    "output_root": "Data_sidis_epip_richcap.inb.qa.new8.nSidis_005036.hipo.root",
    "accumulated_charge": 169255.79009,
    "total_events": 1367327,
    "events_after_PID_Cuts": 787067,
    "Pass_1_PID_Cut_events": 957945,
    "Multiple_Pions_Per_event": 174552,
    "RunTime_in_secs": 6384,
    "timestamp": "2026-04-16T00:02:19.144469704Z"
  },
  "File: Charge_Summary_Data_sidis_epip_richcap.inb.qa.new8.nSidis_005038.hipo.json": {
    "input_file": "nSidis_005038.hipo",
    "output_root": "Data_sidis_epip_richcap.inb.qa.new8.nSidis_005038.hipo.root",
    "accumulated_charge": 379664.98005500005,
    "total_events": 3137563,
    "events_after_PID_Cuts": 1823026,
    "Pass_1_PID_Cut_events": 2211419,
    "Multiple_Pions_Per_event": 405720,
    "RunTime_in_secs": 11813,
    "timestamp": "2026-04-16T01:32:47.782794801Z"
  },
  "File: Charge_Summary_Data_sidis_epip_richcap.inb.qa.new8.nSidis_005039.hipo.json": {
    "input_file": "nSidis_005039.hipo",
    "output_root": "Data_sidis_epip_richcap.inb.qa.new8.nSidis_005039.hipo.root",
    "accumulated_charge": 96867.03218000001,
    "total_events": 801792,
    "events_after_PID_Cuts": 464592,
    "Pass_1_PID_Cut_events": 563159,
    "Multiple_Pions_Per_event": 104179,
    "RunTime_in_secs": 3447,
    "timestamp": "2026-04-15T23:13:21.736674395Z"
  },
  "File: Charge_Summary_Data_sidis_epip_richcap.inb.qa.new8.nSidis_005040.hipo.json": {
    "input_file": "nSidis_005040.hipo",
    "output_root": "Data_sidis_epip_richcap.inb.qa.new8.nSidis_005040.hipo.root",
    "accumulated_charge": 148385.26021,
    "total_events": 1223097,
    "events_after_PID_Cuts": 709861,
    "Pass_1_PID_Cut_events": 861028,
    "Multiple_Pions_Per_event": 159667,
    "RunTime_in_secs": 4785,
    "timestamp": "2026-04-15T23:35:39.646515030Z"
  },
  "File: Charge_Summary_Data_sidis_epip_richcap.inb.qa.new8.nSidis_005041.hipo.json": {
    "input_file": "nSidis_005041.hipo",
    "output_root": "Data_sidis_epip_richcap.inb.qa.new8.nSidis_005041.hipo.root",
    "accumulated_charge": 176654.00028,
    "total_events": 1453071,
    "events_after_PID_Cuts": 843976,
    "Pass_1_PID_Cut_events": 1022803,
    "Multiple_Pions_Per_event": 190400,
    "RunTime_in_secs": 8938,
    "timestamp": "2026-04-16T00:44:52.882847232Z"
  },
  "File: Charge_Summary_Data_sidis_epip_richcap.inb.qa.new8.nSidis_005043.hipo.json": {
    "input_file": "nSidis_005043.hipo",
    "output_root": "Data_sidis_epip_richcap.inb.qa.new8.nSidis_005043.hipo.root",
    "accumulated_charge": 138574.96090000003,
    "total_events": 1145203,
    "events_after_PID_Cuts": 667588,
    "Pass_1_PID_Cut_events": 808480,
    "Multiple_Pions_Per_event": 149230,
    "RunTime_in_secs": 5024,
    "timestamp": "2026-04-15T23:39:39.172836985Z"
  },
  "File: Charge_Summary_Data_sidis_epip_richcap.inb.qa.new8.nSidis_005045.hipo.json": {
    "input_file": "nSidis_005045.hipo",
    "output_root": "Data_sidis_epip_richcap.inb.qa.new8.nSidis_005045.hipo.root",
    "accumulated_charge": 140597.76279,
    "total_events": 1161767,
    "events_after_PID_Cuts": 674477,
    "Pass_1_PID_Cut_events": 817213,
    "Multiple_Pions_Per_event": 152733,
    "RunTime_in_secs": 4033,
    "timestamp": "2026-04-15T23:23:37.504916105Z"
  },
  "File: Charge_Summary_Data_sidis_epip_richcap.inb.qa.new8.nSidis_005046.hipo.json": {
    "input_file": "nSidis_005046.hipo",
    "output_root": "Data_sidis_epip_richcap.inb.qa.new8.nSidis_005046.hipo.root",
    "accumulated_charge": 388785.13999999996,
    "total_events": 3206045,
    "events_after_PID_Cuts": 1856024,
    "Pass_1_PID_Cut_events": 2249177,
    "Multiple_Pions_Per_event": 419832,
    "RunTime_in_secs": 14598,
    "timestamp": "2026-04-16T03:16:45.359904414Z"
  },
  "File: Charge_Summary_Data_sidis_epip_richcap.inb.qa.new8.nSidis_005047.hipo.json": {
    "input_file": "nSidis_005047.hipo",
    "output_root": "Data_sidis_epip_richcap.inb.qa.new8.nSidis_005047.hipo.root",
    "accumulated_charge": 16359.827072000002,
    "total_events": 134593,
    "events_after_PID_Cuts": 77835,
    "Pass_1_PID_Cut_events": 94405,
    "Multiple_Pions_Per_event": 17552,
    "RunTime_in_secs": 559,
    "timestamp": "2026-04-15T23:33:01.108809298Z"
  },
  "File: Charge_Summary_Data_sidis_epip_richcap.inb.qa.new8.nSidis_005051.hipo.json": {
    "input_file": "nSidis_005051.hipo",
    "output_root": "Data_sidis_epip_richcap.inb.qa.new8.nSidis_005051.hipo.root",
    "accumulated_charge": 288649.61416,
    "total_events": 2381490,
    "events_after_PID_Cuts": 1377856,
    "Pass_1_PID_Cut_events": 1670371,
    "Multiple_Pions_Per_event": 311222,
    "RunTime_in_secs": 8983,
    "timestamp": "2026-04-16T02:02:48.940140521Z"
  },
  "File: Charge_Summary_Data_sidis_epip_richcap.inb.qa.new8.nSidis_005052.hipo.json": {
    "input_file": "nSidis_005052.hipo",
    "output_root": "Data_sidis_epip_richcap.inb.qa.new8.nSidis_005052.hipo.root",
    "accumulated_charge": 31329.7292,
    "total_events": 260758,
    "events_after_PID_Cuts": 151108,
    "Pass_1_PID_Cut_events": 183141,
    "Multiple_Pions_Per_event": 33836,
    "RunTime_in_secs": 1088,
    "timestamp": "2026-04-15T23:53:54.702074318Z"
  },
  "File: Charge_Summary_Data_sidis_epip_richcap.inb.qa.new8.nSidis_005053.hipo.json": {
    "input_file": "nSidis_005053.hipo",
    "output_root": "Data_sidis_epip_richcap.inb.qa.new8.nSidis_005053.hipo.root",
    "accumulated_charge": 52127.29184,
    "total_events": 429117,
    "events_after_PID_Cuts": 248301,
    "Pass_1_PID_Cut_events": 301247,
    "Multiple_Pions_Per_event": 56604,
    "RunTime_in_secs": 1593,
    "timestamp": "2026-04-16T00:06:19.534558311Z"
  },
  "File: Charge_Summary_Data_sidis_epip_richcap.inb.qa.new8.nSidis_005116.hipo.json": {
    "input_file": "nSidis_005116.hipo",
    "output_root": "Data_sidis_epip_richcap.inb.qa.new8.nSidis_005116.hipo.root",
    "accumulated_charge": 0.0,
    "total_events": 0,
    "events_after_PID_Cuts": 0,
    "Pass_1_PID_Cut_events": 0,
    "Multiple_Pions_Per_event": 0,
    "RunTime_in_secs": 26,
    "timestamp": "2026-04-15T23:54:25.545643115Z"
  },
  "File: Charge_Summary_Data_sidis_epip_richcap.inb.qa.new8.nSidis_005117.hipo.json": {
    "input_file": "nSidis_005117.hipo",
    "output_root": "Data_sidis_epip_richcap.inb.qa.new8.nSidis_005117.hipo.root",
    "accumulated_charge": 0.0,
    "total_events": 0,
    "events_after_PID_Cuts": 0,
    "Pass_1_PID_Cut_events": 0,
    "Multiple_Pions_Per_event": 0,
    "RunTime_in_secs": 2110,
    "timestamp": "2026-04-16T00:29:40.228073918Z"
  },
  "File: Charge_Summary_Data_sidis_epip_richcap.inb.qa.new8.nSidis_005119.hipo.json": {
    "input_file": "nSidis_005119.hipo",
    "output_root": "Data_sidis_epip_richcap.inb.qa.new8.nSidis_005119.hipo.root",
    "accumulated_charge": 0.0,
    "total_events": 0,
    "events_after_PID_Cuts": 0,
    "Pass_1_PID_Cut_events": 0,
    "Multiple_Pions_Per_event": 0,
    "RunTime_in_secs": 52,
    "timestamp": "2026-04-16T00:03:15.933924752Z"
  },
  "File: Charge_Summary_Data_sidis_epip_richcap.inb.qa.new8.nSidis_005120.hipo.json": {
    "input_file": "nSidis_005120.hipo",
    "output_root": "Data_sidis_epip_richcap.inb.qa.new8.nSidis_005120.hipo.root",
    "accumulated_charge": 78469.18921,
    "total_events": 648391,
    "events_after_PID_Cuts": 375722,
    "Pass_1_PID_Cut_events": 455424,
    "Multiple_Pions_Per_event": 84280,
    "RunTime_in_secs": 2697,
    "timestamp": "2026-04-16T00:48:16.270335376Z"
  },
  "File: Charge_Summary_Data_sidis_epip_richcap.inb.qa.new8.nSidis_005124.hipo.json": {
    "input_file": "nSidis_005124.hipo",
    "output_root": "Data_sidis_epip_richcap.inb.qa.new8.nSidis_005124.hipo.root",
    "accumulated_charge": 397189.53306,
    "total_events": 3254873,
    "events_after_PID_Cuts": 1880282,
    "Pass_1_PID_Cut_events": 2280605,
    "Multiple_Pions_Per_event": 425112,
    "RunTime_in_secs": 13888,
    "timestamp": "2026-04-16T03:57:54.427797845Z"
  },
  "File: Charge_Summary_Data_sidis_epip_richcap.inb.qa.new8.nSidis_005125.hipo.json": {
    "input_file": "nSidis_005125.hipo",
    "output_root": "Data_sidis_epip_richcap.inb.qa.new8.nSidis_005125.hipo.root",
    "accumulated_charge": 396820.772696,
    "total_events": 3251056,
    "events_after_PID_Cuts": 1883931,
    "Pass_1_PID_Cut_events": 2283063,
    "Multiple_Pions_Per_event": 424412,
    "RunTime_in_secs": 13584,
    "timestamp": "2026-04-16T04:16:10.056638552Z"
  },
  "File: Charge_Summary_Data_sidis_epip_richcap.inb.qa.new8.nSidis_005126.hipo.json": {
    "input_file": "nSidis_005126.hipo",
    "output_root": "Data_sidis_epip_richcap.inb.qa.new8.nSidis_005126.hipo.root",
    "accumulated_charge": 397631.1956,
    "total_events": 3248668,
    "events_after_PID_Cuts": 1880679,
    "Pass_1_PID_Cut_events": 2281123,
    "Multiple_Pions_Per_event": 423637,
    "RunTime_in_secs": 12745,
    "timestamp": "2026-04-16T04:17:23.966160280Z"
  },
  "File: Charge_Summary_Data_sidis_epip_richcap.inb.qa.new8.nSidis_005127.hipo.json": {
    "input_file": "nSidis_005127.hipo",
    "output_root": "Data_sidis_epip_richcap.inb.qa.new8.nSidis_005127.hipo.root",
    "accumulated_charge": 0.0,
    "total_events": 0,
    "events_after_PID_Cuts": 0,
    "Pass_1_PID_Cut_events": 0,
    "Multiple_Pions_Per_event": 0,
    "RunTime_in_secs": 30,
    "timestamp": "2026-04-16T00:48:52.443649102Z"
  },
  "File: Charge_Summary_Data_sidis_epip_richcap.inb.qa.new8.nSidis_005128.hipo.json": {
    "input_file": "nSidis_005128.hipo",
    "output_root": "Data_sidis_epip_richcap.inb.qa.new8.nSidis_005128.hipo.root",
    "accumulated_charge": 399283.95668,
    "total_events": 3256542,
    "events_after_PID_Cuts": 1884274,
    "Pass_1_PID_Cut_events": 2284214,
    "Multiple_Pions_Per_event": 424378,
    "RunTime_in_secs": 13234,
    "timestamp": "2026-04-16T04:29:32.025023682Z"
  },
  "File: Charge_Summary_Data_sidis_epip_richcap.inb.qa.new8.nSidis_005129.hipo.json": {
    "input_file": "nSidis_005129.hipo",
    "output_root": "Data_sidis_epip_richcap.inb.qa.new8.nSidis_005129.hipo.root",
    "accumulated_charge": 167978.50795199999,
    "total_events": 1377755,
    "events_after_PID_Cuts": 798777,
    "Pass_1_PID_Cut_events": 968075,
    "Multiple_Pions_Per_event": 179452,
    "RunTime_in_secs": 5802,
    "timestamp": "2026-04-16T03:09:36.711617097Z"
  },
  "File: Charge_Summary_Data_sidis_epip_richcap.inb.qa.new8.nSidis_005130.hipo.json": {
    "input_file": "nSidis_005130.hipo",
    "output_root": "Data_sidis_epip_richcap.inb.qa.new8.nSidis_005130.hipo.root",
    "accumulated_charge": 397792.63175000006,
    "total_events": 3248105,
    "events_after_PID_Cuts": 1881868,
    "Pass_1_PID_Cut_events": 2282471,
    "Multiple_Pions_Per_event": 423241,
    "RunTime_in_secs": 12476,
    "timestamp": "2026-04-16T05:30:51.141156972Z"
  },
  "File: Charge_Summary_Data_sidis_epip_richcap.inb.qa.new8.nSidis_005137.hipo.json": {
    "input_file": "nSidis_005137.hipo",
    "output_root": "Data_sidis_epip_richcap.inb.qa.new8.nSidis_005137.hipo.root",
    "accumulated_charge": 0.0,
    "total_events": 0,
    "events_after_PID_Cuts": 0,
    "Pass_1_PID_Cut_events": 0,
    "Multiple_Pions_Per_event": 0,
    "RunTime_in_secs": 15,
    "timestamp": "2026-04-16T03:09:57.624912728Z"
  },
  "File: Charge_Summary_Data_sidis_epip_richcap.inb.qa.new8.nSidis_005138.hipo.json": {
    "input_file": "nSidis_005138.hipo",
    "output_root": "Data_sidis_epip_richcap.inb.qa.new8.nSidis_005138.hipo.root",
    "accumulated_charge": 0.0,
    "total_events": 0,
    "events_after_PID_Cuts": 0,
    "Pass_1_PID_Cut_events": 0,
    "Multiple_Pions_Per_event": 0,
    "RunTime_in_secs": 25,
    "timestamp": "2026-04-16T03:10:28.498855924Z"
  },
  "File: Charge_Summary_Data_sidis_epip_richcap.inb.qa.new8.nSidis_005139.hipo.json": {
    "input_file": "nSidis_005139.hipo",
    "output_root": "Data_sidis_epip_richcap.inb.qa.new8.nSidis_005139.hipo.root",
    "accumulated_charge": 140419.109952,
    "total_events": 1151324,
    "events_after_PID_Cuts": 664784,
    "Pass_1_PID_Cut_events": 806068,
    "Multiple_Pions_Per_event": 149840,
    "RunTime_in_secs": 4596,
    "timestamp": "2026-04-16T04:27:09.447804988Z"
  },
  "File: Charge_Summary_Data_sidis_epip_richcap.inb.qa.new8.nSidis_005153.hipo.json": {
    "input_file": "nSidis_005153.hipo",
    "output_root": "Data_sidis_epip_richcap.inb.qa.new8.nSidis_005153.hipo.root",
    "accumulated_charge": 69118.91758,
    "total_events": 564240,
    "events_after_PID_Cuts": 325308,
    "Pass_1_PID_Cut_events": 393757,
    "Multiple_Pions_Per_event": 73297,
    "RunTime_in_secs": 2272,
    "timestamp": "2026-04-16T03:54:43.798551039Z"
  },
  "File: Charge_Summary_Data_sidis_epip_richcap.inb.qa.new8.nSidis_005158.hipo.json": {
    "input_file": "nSidis_005158.hipo",
    "output_root": "Data_sidis_epip_richcap.inb.qa.new8.nSidis_005158.hipo.root",
    "accumulated_charge": 38852.255209999996,
    "total_events": 317090,
    "events_after_PID_Cuts": 184619,
    "Pass_1_PID_Cut_events": 223230,
    "Multiple_Pions_Per_event": 41362,
    "RunTime_in_secs": 1373,
    "timestamp": "2026-04-16T04:17:43.210635279Z"
  },
  "File: Charge_Summary_Data_sidis_epip_richcap.inb.qa.new8.nSidis_005159.hipo.json": {
    "input_file": "nSidis_005159.hipo",
    "output_root": "Data_sidis_epip_richcap.inb.qa.new8.nSidis_005159.hipo.root",
    "accumulated_charge": 246279.72610400003,
    "total_events": 2024428,
    "events_after_PID_Cuts": 1168236,
    "Pass_1_PID_Cut_events": 1417453,
    "Multiple_Pions_Per_event": 263845,
    "RunTime_in_secs": 6611,
    "timestamp": "2026-04-16T05:48:11.599616322Z"
  },
  "File: Charge_Summary_Data_sidis_epip_richcap.inb.qa.new8.nSidis_005160.hipo.json": {
    "input_file": "nSidis_005160.hipo",
    "output_root": "Data_sidis_epip_richcap.inb.qa.new8.nSidis_005160.hipo.root",
    "accumulated_charge": 174010.389108,
    "total_events": 1422335,
    "events_after_PID_Cuts": 821772,
    "Pass_1_PID_Cut_events": 996431,
    "Multiple_Pions_Per_event": 185190,
    "RunTime_in_secs": 4671,
    "timestamp": "2026-04-16T05:34:07.631670415Z"
  },
  "File: Charge_Summary_Data_sidis_epip_richcap.inb.qa.new8.nSidis_005162.hipo.json": {
    "input_file": "nSidis_005162.hipo",
    "output_root": "Data_sidis_epip_richcap.inb.qa.new8.nSidis_005162.hipo.root",
    "accumulated_charge": 79813.75136,
    "total_events": 647590,
    "events_after_PID_Cuts": 374429,
    "Pass_1_PID_Cut_events": 453713,
    "Multiple_Pions_Per_event": 84778,
    "RunTime_in_secs": 2160,
    "timestamp": "2026-04-16T04:53:30.201551402Z"
  },
  "File: Charge_Summary_Data_sidis_epip_richcap.inb.qa.new8.nSidis_005163.hipo.json": {
    "input_file": "nSidis_005163.hipo",
    "output_root": "Data_sidis_epip_richcap.inb.qa.new8.nSidis_005163.hipo.root",
    "accumulated_charge": 401075.4119,
    "total_events": 3278378,
    "events_after_PID_Cuts": 1892435,
    "Pass_1_PID_Cut_events": 2294418,
    "Multiple_Pions_Per_event": 427248,
    "RunTime_in_secs": 10152,
    "timestamp": "2026-04-16T07:07:02.158092486Z"
  },
  "File: Charge_Summary_Data_sidis_epip_richcap.inb.qa.new8.nSidis_005164.hipo.json": {
    "input_file": "nSidis_005164.hipo",
    "output_root": "Data_sidis_epip_richcap.inb.qa.new8.nSidis_005164.hipo.root",
    "accumulated_charge": 6592.61917,
    "total_events": 53275,
    "events_after_PID_Cuts": 30532,
    "Pass_1_PID_Cut_events": 37042,
    "Multiple_Pions_Per_event": 6903,
    "RunTime_in_secs": 196,
    "timestamp": "2026-04-16T04:30:30.354471088Z"
  },
  "File: Charge_Summary_Data_sidis_epip_richcap.inb.qa.new8.nSidis_005165.hipo.json": {
    "input_file": "nSidis_005165.hipo",
    "output_root": "Data_sidis_epip_richcap.inb.qa.new8.nSidis_005165.hipo.root",
    "accumulated_charge": 270945.450885,
    "total_events": 2215609,
    "events_after_PID_Cuts": 1279874,
    "Pass_1_PID_Cut_events": 1550264,
    "Multiple_Pions_Per_event": 289131,
    "RunTime_in_secs": 6878,
    "timestamp": "2026-04-16T06:24:15.172866331Z"
  },
  "File: Charge_Summary_Data_sidis_epip_richcap.inb.qa.new8.nSidis_005166.hipo.json": {
    "input_file": "nSidis_005166.hipo",
    "output_root": "Data_sidis_epip_richcap.inb.qa.new8.nSidis_005166.hipo.root",
    "accumulated_charge": 402766.9773,
    "total_events": 3287706,
    "events_after_PID_Cuts": 1899018,
    "Pass_1_PID_Cut_events": 2300317,
    "Multiple_Pions_Per_event": 427848,
    "RunTime_in_secs": 9916,
    "timestamp": "2026-04-16T07:15:50.955338502Z"
  },
  "File: Charge_Summary_Data_sidis_epip_richcap.inb.qa.new8.nSidis_005167.hipo.json": {
    "input_file": "nSidis_005167.hipo",
    "output_root": "Data_sidis_epip_richcap.inb.qa.new8.nSidis_005167.hipo.root",
    "accumulated_charge": 398691.6208,
    "total_events": 3262688,
    "events_after_PID_Cuts": 1882968,
    "Pass_1_PID_Cut_events": 2282198,
    "Multiple_Pions_Per_event": 426213,
    "RunTime_in_secs": 10056,
    "timestamp": "2026-04-16T07:41:11.085733893Z"
  },
  "File: Charge_Summary_Data_sidis_epip_richcap.inb.qa.new8.nSidis_005168.hipo.json": {
    "input_file": "nSidis_005168.hipo",
    "output_root": "Data_sidis_epip_richcap.inb.qa.new8.nSidis_005168.hipo.root",
    "accumulated_charge": 203543.412244,
    "total_events": 1662666,
    "events_after_PID_Cuts": 959440,
    "Pass_1_PID_Cut_events": 1162283,
    "Multiple_Pions_Per_event": 217304,
    "RunTime_in_secs": 5362,
    "timestamp": "2026-04-16T07:00:18.670673413Z"
  },
  "File: Charge_Summary_Data_sidis_epip_richcap.inb.qa.new8.nSidis_005169.hipo.json": {
    "input_file": "nSidis_005169.hipo",
    "output_root": "Data_sidis_epip_richcap.inb.qa.new8.nSidis_005169.hipo.root",
    "accumulated_charge": 406886.90818,
    "total_events": 3325524,
    "events_after_PID_Cuts": 1919479,
    "Pass_1_PID_Cut_events": 2324709,
    "Multiple_Pions_Per_event": 434074,
    "RunTime_in_secs": 10955,
    "timestamp": "2026-04-16T08:36:47.982682041Z"
  },
  "File: Charge_Summary_Data_sidis_epip_richcap.inb.qa.new8.nSidis_005180.hipo.json": {
    "input_file": "nSidis_005180.hipo",
    "output_root": "Data_sidis_epip_richcap.inb.qa.new8.nSidis_005180.hipo.root",
    "accumulated_charge": 222583.19053,
    "total_events": 1839616,
    "events_after_PID_Cuts": 1066959,
    "Pass_1_PID_Cut_events": 1293745,
    "Multiple_Pions_Per_event": 240193,
    "RunTime_in_secs": 5469,
    "timestamp": "2026-04-16T07:19:24.690122Z"
  },
  "File: Charge_Summary_Data_sidis_epip_richcap.inb.qa.new8.nSidis_005181.hipo.json": {
    "input_file": "nSidis_005181.hipo",
    "output_root": "Data_sidis_epip_richcap.inb.qa.new8.nSidis_005181.hipo.root",
    "accumulated_charge": 367788.684108,
    "total_events": 3025577,
    "events_after_PID_Cuts": 1759041,
    "Pass_1_PID_Cut_events": 2127952,
    "Multiple_Pions_Per_event": 394534,
    "RunTime_in_secs": 8842,
    "timestamp": "2026-04-16T08:51:42.295423256Z"
  },
  "File: Charge_Summary_Data_sidis_epip_richcap.inb.qa.new8.nSidis_005182.hipo.json": {
    "input_file": "nSidis_005182.hipo",
    "output_root": "Data_sidis_epip_richcap.inb.qa.new8.nSidis_005182.hipo.root",
    "accumulated_charge": 75612.97073399999,
    "total_events": 623801,
    "events_after_PID_Cuts": 362069,
    "Pass_1_PID_Cut_events": 438057,
    "Multiple_Pions_Per_event": 81414,
    "RunTime_in_secs": 2017,
    "timestamp": "2026-04-16T07:34:00.140423768Z"
  },
  "File: Charge_Summary_Data_sidis_epip_richcap.inb.qa.new8.nSidis_005183.hipo.json": {
    "input_file": "nSidis_005183.hipo",
    "output_root": "Data_sidis_epip_richcap.inb.qa.new8.nSidis_005183.hipo.root",
    "accumulated_charge": 327373.14788,
    "total_events": 2682645,
    "events_after_PID_Cuts": 1558745,
    "Pass_1_PID_Cut_events": 1884671,
    "Multiple_Pions_Per_event": 349637,
    "RunTime_in_secs": 8234,
    "timestamp": "2026-04-16T09:24:20.982454713Z"
  },
  "File: Charge_Summary_Data_sidis_epip_richcap.inb.qa.new8.nSidis_005190.hipo.json": {
    "input_file": "nSidis_005190.hipo",
    "output_root": "Data_sidis_epip_richcap.inb.qa.new8.nSidis_005190.hipo.root",
    "accumulated_charge": 186396.78596,
    "total_events": 1490241,
    "events_after_PID_Cuts": 871358,
    "Pass_1_PID_Cut_events": 1053065,
    "Multiple_Pions_Per_event": 188229,
    "RunTime_in_secs": 4804,
    "timestamp": "2026-04-16T08:36:00.262722941Z"
  },
  "File: Charge_Summary_Data_sidis_epip_richcap.inb.qa.new8.nSidis_005191.hipo.json": {
    "input_file": "nSidis_005191.hipo",
    "output_root": "Data_sidis_epip_richcap.inb.qa.new8.nSidis_005191.hipo.root",
    "accumulated_charge": 431956.60890000005,
    "total_events": 3455398,
    "events_after_PID_Cuts": 2016958,
    "Pass_1_PID_Cut_events": 2438161,
    "Multiple_Pions_Per_event": 436092,
    "RunTime_in_secs": 10346,
    "timestamp": "2026-04-16T10:11:54.881928693Z"
  },
  "File: Charge_Summary_Data_sidis_epip_richcap.inb.qa.new8.nSidis_005193.hipo.json": {
    "input_file": "nSidis_005193.hipo",
    "output_root": "Data_sidis_epip_richcap.inb.qa.new8.nSidis_005193.hipo.root",
    "accumulated_charge": 152602.40459999998,
    "total_events": 1247282,
    "events_after_PID_Cuts": 727310,
    "Pass_1_PID_Cut_events": 879350,
    "Multiple_Pions_Per_event": 159221,
    "RunTime_in_secs": 4458,
    "timestamp": "2026-04-16T08:48:21.560762800Z"
  },
  "File: Charge_Summary_Data_sidis_epip_richcap.inb.qa.new8.nSidis_005194.hipo.json": {
    "input_file": "nSidis_005194.hipo",
    "output_root": "Data_sidis_epip_richcap.inb.qa.new8.nSidis_005194.hipo.root",
    "accumulated_charge": 0.0,
    "total_events": 0,
    "events_after_PID_Cuts": 0,
    "Pass_1_PID_Cut_events": 0,
    "Multiple_Pions_Per_event": 0,
    "RunTime_in_secs": 43,
    "timestamp": "2026-04-16T07:41:57.879528759Z"
  },
  "File: Charge_Summary_Data_sidis_epip_richcap.inb.qa.new8.nSidis_005195.hipo.json": {
    "input_file": "nSidis_005195.hipo",
    "output_root": "Data_sidis_epip_richcap.inb.qa.new8.nSidis_005195.hipo.root",
    "accumulated_charge": 76574.15568000001,
    "total_events": 627421,
    "events_after_PID_Cuts": 364260,
    "Pass_1_PID_Cut_events": 441072,
    "Multiple_Pions_Per_event": 80461,
    "RunTime_in_secs": 2091,
    "timestamp": "2026-04-16T08:16:52.782917008Z"
  },
  "File: Charge_Summary_Data_sidis_epip_richcap.inb.qa.new8.nSidis_005196.hipo.json": {
    "input_file": "nSidis_005196.hipo",
    "output_root": "Data_sidis_epip_richcap.inb.qa.new8.nSidis_005196.hipo.root",
    "accumulated_charge": 412108.50276999996,
    "total_events": 3329904,
    "events_after_PID_Cuts": 1934839,
    "Pass_1_PID_Cut_events": 2339845,
    "Multiple_Pions_Per_event": 424481,
    "RunTime_in_secs": 9225,
    "timestamp": "2026-04-16T10:50:41.903322426Z"
  },
  "File: Charge_Summary_Data_sidis_epip_richcap.inb.qa.new8.nSidis_005197.hipo.json": {
    "input_file": "nSidis_005197.hipo",
    "output_root": "Data_sidis_epip_richcap.inb.qa.new8.nSidis_005197.hipo.root",
    "accumulated_charge": 414492.21926,
    "total_events": 3365135,
    "events_after_PID_Cuts": 1953026,
    "Pass_1_PID_Cut_events": 2363315,
    "Multiple_Pions_Per_event": 429108,
    "RunTime_in_secs": 9481,
    "timestamp": "2026-04-16T11:14:06.292362561Z"
  },
  "File: Charge_Summary_Data_sidis_epip_richcap.inb.qa.new8.nSidis_005198.hipo.json": {
    "input_file": "nSidis_005198.hipo",
    "output_root": "Data_sidis_epip_richcap.inb.qa.new8.nSidis_005198.hipo.root",
    "accumulated_charge": 411692.49131499993,
    "total_events": 3313901,
    "events_after_PID_Cuts": 1919048,
    "Pass_1_PID_Cut_events": 2323014,
    "Multiple_Pions_Per_event": 423231,
    "RunTime_in_secs": 9214,
    "timestamp": "2026-04-16T11:10:26.120433714Z"
  },
  "File: Charge_Summary_Data_sidis_epip_richcap.inb.qa.new8.nSidis_005199.hipo.json": {
    "input_file": "nSidis_005199.hipo",
    "output_root": "Data_sidis_epip_richcap.inb.qa.new8.nSidis_005199.hipo.root",
    "accumulated_charge": 412227.8212,
    "total_events": 3337951,
    "events_after_PID_Cuts": 1934424,
    "Pass_1_PID_Cut_events": 2341293,
    "Multiple_Pions_Per_event": 426303,
    "RunTime_in_secs": 9307,
    "timestamp": "2026-04-16T11:23:33.307472503Z"
  },
  "File: Charge_Summary_Data_sidis_epip_richcap.inb.qa.new8.nSidis_005200.hipo.json": {
    "input_file": "nSidis_005200.hipo",
    "output_root": "Data_sidis_epip_richcap.inb.qa.new8.nSidis_005200.hipo.root",
    "accumulated_charge": 153306.22798999998,
    "total_events": 1240216,
    "events_after_PID_Cuts": 717264,
    "Pass_1_PID_Cut_events": 867917,
    "Multiple_Pions_Per_event": 158295,
    "RunTime_in_secs": 3548,
    "timestamp": "2026-04-16T09:50:54.312075397Z"
  },
  "File: Charge_Summary_Data_sidis_epip_richcap.inb.qa.new8.nSidis_005201.hipo.json": {
    "input_file": "nSidis_005201.hipo",
    "output_root": "Data_sidis_epip_richcap.inb.qa.new8.nSidis_005201.hipo.root",
    "accumulated_charge": 81007.08568,
    "total_events": 658207,
    "events_after_PID_Cuts": 380865,
    "Pass_1_PID_Cut_events": 460838,
    "Multiple_Pions_Per_event": 84232,
    "RunTime_in_secs": 1882,
    "timestamp": "2026-04-16T09:55:48.064138541Z"
  },
  "File: Charge_Summary_Data_sidis_epip_richcap.inb.qa.new8.nSidis_005202.hipo.json": {
    "input_file": "nSidis_005202.hipo",
    "output_root": "Data_sidis_epip_richcap.inb.qa.new8.nSidis_005202.hipo.root",
    "accumulated_charge": 412689.4524,
    "total_events": 3333539,
    "events_after_PID_Cuts": 1930118,
    "Pass_1_PID_Cut_events": 2334928,
    "Multiple_Pions_Per_event": 425698,
    "RunTime_in_secs": 9083,
    "timestamp": "2026-04-16T12:22:22.006502998Z"
  },
  "File: Charge_Summary_Data_sidis_epip_richcap.inb.qa.new8.nSidis_005203.hipo.json": {
    "input_file": "nSidis_005203.hipo",
    "output_root": "Data_sidis_epip_richcap.inb.qa.new8.nSidis_005203.hipo.root",
    "accumulated_charge": 414305.9910599999,
    "total_events": 3345614,
    "events_after_PID_Cuts": 1939210,
    "Pass_1_PID_Cut_events": 2344687,
    "Multiple_Pions_Per_event": 426996,
    "RunTime_in_secs": 9183,
    "timestamp": "2026-04-16T12:28:55.402067204Z"
  },
  "File: Charge_Summary_Data_sidis_epip_richcap.inb.qa.new8.nSidis_005204.hipo.json": {
    "input_file": "nSidis_005204.hipo",
    "output_root": "Data_sidis_epip_richcap.inb.qa.new8.nSidis_005204.hipo.root",
    "accumulated_charge": 400697.88178000005,
    "total_events": 3239448,
    "events_after_PID_Cuts": 1873673,
    "Pass_1_PID_Cut_events": 2267650,
    "Multiple_Pions_Per_event": 413882,
    "RunTime_in_secs": 9226,
    "timestamp": "2026-04-16T12:45:45.556067492Z"
  },
  "File: Charge_Summary_Data_sidis_epip_richcap.inb.qa.new8.nSidis_005205.hipo.json": {
    "input_file": "nSidis_005205.hipo",
    "output_root": "Data_sidis_epip_richcap.inb.qa.new8.nSidis_005205.hipo.root",
    "accumulated_charge": 90771.31178,
    "total_events": 728102,
    "events_after_PID_Cuts": 421153,
    "Pass_1_PID_Cut_events": 510068,
    "Multiple_Pions_Per_event": 92680,
    "RunTime_in_secs": 2146,
    "timestamp": "2026-04-16T11:26:34.817018163Z"
  },
  "File: Charge_Summary_Data_sidis_epip_richcap.inb.qa.new8.nSidis_005206.hipo.json": {
    "input_file": "nSidis_005206.hipo",
    "output_root": "Data_sidis_epip_richcap.inb.qa.new8.nSidis_005206.hipo.root",
    "accumulated_charge": 288598.65576,
    "total_events": 2328932,
    "events_after_PID_Cuts": 1348193,
    "Pass_1_PID_Cut_events": 1630759,
    "Multiple_Pions_Per_event": 296681,
    "RunTime_in_secs": 6392,
    "timestamp": "2026-04-16T12:57:03.057410999Z"
  },
  "File: Charge_Summary_Data_sidis_epip_richcap.inb.qa.new8.nSidis_005208.hipo.json": {
    "input_file": "nSidis_005208.hipo",
    "output_root": "Data_sidis_epip_richcap.inb.qa.new8.nSidis_005208.hipo.root",
    "accumulated_charge": 332956.482576,
    "total_events": 2700637,
    "events_after_PID_Cuts": 1564029,
    "Pass_1_PID_Cut_events": 1892711,
    "Multiple_Pions_Per_event": 345634,
    "RunTime_in_secs": 7748,
    "timestamp": "2026-04-16T13:23:19.444523615Z"
  },
  "File: Charge_Summary_Data_sidis_epip_richcap.inb.qa.new8.nSidis_005211.hipo.json": {
    "input_file": "nSidis_005211.hipo",
    "output_root": "Data_sidis_epip_richcap.inb.qa.new8.nSidis_005211.hipo.root",
    "accumulated_charge": 88950.82552,
    "total_events": 721441,
    "events_after_PID_Cuts": 418129,
    "Pass_1_PID_Cut_events": 506179,
    "Multiple_Pions_Per_event": 92112,
    "RunTime_in_secs": 1942,
    "timestamp": "2026-04-16T11:56:00.690616118Z"
  },
  "File: Charge_Summary_Data_sidis_epip_richcap.inb.qa.new8.nSidis_005212.hipo.json": {
    "input_file": "nSidis_005212.hipo",
    "output_root": "Data_sidis_epip_richcap.inb.qa.new8.nSidis_005212.hipo.root",
    "accumulated_charge": 400507.8798453,
    "total_events": 3271604,
    "events_after_PID_Cuts": 1892593,
    "Pass_1_PID_Cut_events": 2291296,
    "Multiple_Pions_Per_event": 420195,
    "RunTime_in_secs": 9601,
    "timestamp": "2026-04-16T14:06:40.778953805Z"
  },
  "File: Charge_Summary_Data_sidis_epip_richcap.inb.qa.new8.nSidis_005215.hipo.json": {
    "input_file": "nSidis_005215.hipo",
    "output_root": "Data_sidis_epip_richcap.inb.qa.new8.nSidis_005215.hipo.root",
    "accumulated_charge": 0.0,
    "total_events": 0,
    "events_after_PID_Cuts": 0,
    "Pass_1_PID_Cut_events": 0,
    "Multiple_Pions_Per_event": 0,
    "RunTime_in_secs": 72,
    "timestamp": "2026-04-16T11:57:17.258475420Z"
  },
  "File: Charge_Summary_Data_sidis_epip_richcap.inb.qa.new8.nSidis_005216.hipo.json": {
    "input_file": "nSidis_005216.hipo",
    "output_root": "Data_sidis_epip_richcap.inb.qa.new8.nSidis_005216.hipo.root",
    "accumulated_charge": 165644.8011,
    "total_events": 1342321,
    "events_after_PID_Cuts": 777097,
    "Pass_1_PID_Cut_events": 939987,
    "Multiple_Pions_Per_event": 172483,
    "RunTime_in_secs": 3630,
    "timestamp": "2026-04-16T12:57:50.942167801Z"
  },
  "File: Charge_Summary_Data_sidis_epip_richcap.inb.qa.new8.nSidis_005219.hipo.json": {
    "input_file": "nSidis_005219.hipo",
    "output_root": "Data_sidis_epip_richcap.inb.qa.new8.nSidis_005219.hipo.root",
    "accumulated_charge": 385882.09796000004,
    "total_events": 3133829,
    "events_after_PID_Cuts": 1815601,
    "Pass_1_PID_Cut_events": 2193112,
    "Multiple_Pions_Per_event": 402077,
    "RunTime_in_secs": 8825,
    "timestamp": "2026-04-16T14:49:31.326821943Z"
  },
  "File: Charge_Summary_Data_sidis_epip_richcap.inb.qa.new8.nSidis_005220.hipo.json": {
    "input_file": "nSidis_005220.hipo",
    "output_root": "Data_sidis_epip_richcap.inb.qa.new8.nSidis_005220.hipo.root",
    "accumulated_charge": 350595.95763,
    "total_events": 2858991,
    "events_after_PID_Cuts": 1658687,
    "Pass_1_PID_Cut_events": 2004681,
    "Multiple_Pions_Per_event": 368438,
    "RunTime_in_secs": 8561,
    "timestamp": "2026-04-16T14:51:40.421679406Z"
  },
  "File: Charge_Summary_Data_sidis_epip_richcap.inb.qa.new8.nSidis_005221.hipo.json": {
    "input_file": "nSidis_005221.hipo",
    "output_root": "Data_sidis_epip_richcap.inb.qa.new8.nSidis_005221.hipo.root",
    "accumulated_charge": 389903.26823179994,
    "total_events": 3179278,
    "events_after_PID_Cuts": 1844993,
    "Pass_1_PID_Cut_events": 2227362,
    "Multiple_Pions_Per_event": 410867,
    "RunTime_in_secs": 9660,
    "timestamp": "2026-04-16T15:26:51.002790827Z"
  },
  "File: Charge_Summary_Data_sidis_epip_richcap.inb.qa.new8.nSidis_005222.hipo.json": {
    "input_file": "nSidis_005222.hipo",
    "output_root": "Data_sidis_epip_richcap.inb.qa.new8.nSidis_005222.hipo.root",
    "accumulated_charge": 388332.98142,
    "total_events": 3159748,
    "events_after_PID_Cuts": 1833002,
    "Pass_1_PID_Cut_events": 2214630,
    "Multiple_Pions_Per_event": 407642,
    "RunTime_in_secs": 9132,
    "timestamp": "2026-04-16T15:29:19.761192195Z"
  },
  "File: Charge_Summary_Data_sidis_epip_richcap.inb.qa.new8.nSidis_005223.hipo.json": {
    "input_file": "nSidis_005223.hipo",
    "output_root": "Data_sidis_epip_richcap.inb.qa.new8.nSidis_005223.hipo.root",
    "accumulated_charge": 136871.67114000002,
    "total_events": 1122805,
    "events_after_PID_Cuts": 652458,
    "Pass_1_PID_Cut_events": 787770,
    "Multiple_Pions_Per_event": 145246,
    "RunTime_in_secs": 3298,
    "timestamp": "2026-04-16T13:54:14.605368004Z"
  },
  "File: Charge_Summary_Data_sidis_epip_richcap.inb.qa.new8.nSidis_005225.hipo.json": {
    "input_file": "nSidis_005225.hipo",
    "output_root": "Data_sidis_epip_richcap.inb.qa.new8.nSidis_005225.hipo.root",
    "accumulated_charge": 0.0,
    "total_events": 0,
    "events_after_PID_Cuts": 0,
    "Pass_1_PID_Cut_events": 0,
    "Multiple_Pions_Per_event": 0,
    "RunTime_in_secs": 42,
    "timestamp": "2026-04-16T13:24:06.215292852Z"
  },
  "File: Charge_Summary_Data_sidis_epip_richcap.inb.qa.new8.nSidis_005229.hipo.json": {
    "input_file": "nSidis_005229.hipo",
    "output_root": "Data_sidis_epip_richcap.inb.qa.new8.nSidis_005229.hipo.root",
    "accumulated_charge": 0.0,
    "total_events": 0,
    "events_after_PID_Cuts": 0,
    "Pass_1_PID_Cut_events": 0,
    "Multiple_Pions_Per_event": 0,
    "RunTime_in_secs": 23,
    "timestamp": "2026-04-16T13:24:33.171347Z"
  },
  "File: Charge_Summary_Data_sidis_epip_richcap.inb.qa.new8.nSidis_005230.hipo.json": {
    "input_file": "nSidis_005230.hipo",
    "output_root": "Data_sidis_epip_richcap.inb.qa.new8.nSidis_005230.hipo.root",
    "accumulated_charge": 385677.42767,
    "total_events": 3118145,
    "events_after_PID_Cuts": 1807810,
    "Pass_1_PID_Cut_events": 2185542,
    "Multiple_Pions_Per_event": 399955,
    "RunTime_in_secs": 9675,
    "timestamp": "2026-04-16T16:05:52.460327002Z"
  },
  "File: Charge_Summary_Data_sidis_epip_richcap.inb.qa.new8.nSidis_005231.hipo.json": {
    "input_file": "nSidis_005231.hipo",
    "output_root": "Data_sidis_epip_richcap.inb.qa.new8.nSidis_005231.hipo.root",
    "accumulated_charge": 392511.4974,
    "total_events": 3193073,
    "events_after_PID_Cuts": 1849689,
    "Pass_1_PID_Cut_events": 2235682,
    "Multiple_Pions_Per_event": 411617,
    "RunTime_in_secs": 9865,
    "timestamp": "2026-04-16T16:38:44.558404584Z"
  },
  "File: Charge_Summary_Data_sidis_epip_richcap.inb.qa.new8.nSidis_005232.hipo.json": {
    "input_file": "nSidis_005232.hipo",
    "output_root": "Data_sidis_epip_richcap.inb.qa.new8.nSidis_005232.hipo.root",
    "accumulated_charge": 389980.8238,
    "total_events": 3181230,
    "events_after_PID_Cuts": 1842947,
    "Pass_1_PID_Cut_events": 2227561,
    "Multiple_Pions_Per_event": 410022,
    "RunTime_in_secs": 9259,
    "timestamp": "2026-04-16T16:41:03.973807405Z"
  },
  "File: Charge_Summary_Data_sidis_epip_richcap.inb.qa.new8.nSidis_005233.hipo.json": {
    "input_file": "nSidis_005233.hipo",
    "output_root": "Data_sidis_epip_richcap.inb.qa.new8.nSidis_005233.hipo.root",
    "accumulated_charge": 388346.14471470006,
    "total_events": 3137681,
    "events_after_PID_Cuts": 1817923,
    "Pass_1_PID_Cut_events": 2197130,
    "Multiple_Pions_Per_event": 403190,
    "RunTime_in_secs": 9082,
    "timestamp": "2026-04-16T17:20:58.492573560Z"
  },
  "File: Charge_Summary_Data_sidis_epip_richcap.inb.qa.new8.nSidis_005234.hipo.json": {
    "input_file": "nSidis_005234.hipo",
    "output_root": "Data_sidis_epip_richcap.inb.qa.new8.nSidis_005234.hipo.root",
    "accumulated_charge": 392375.98978400003,
    "total_events": 3173673,
    "events_after_PID_Cuts": 1840506,
    "Pass_1_PID_Cut_events": 2223390,
    "Multiple_Pions_Per_event": 407279,
    "RunTime_in_secs": 9685,
    "timestamp": "2026-04-16T17:33:10.656369057Z"
  },
  "File: Charge_Summary_Data_sidis_epip_richcap.inb.qa.new8.nSidis_005235.hipo.json": {
    "input_file": "nSidis_005235.hipo",
    "output_root": "Data_sidis_epip_richcap.inb.qa.new8.nSidis_005235.hipo.root",
    "accumulated_charge": 147646.70855,
    "total_events": 1187964,
    "events_after_PID_Cuts": 686479,
    "Pass_1_PID_Cut_events": 830430,
    "Multiple_Pions_Per_event": 152189,
    "RunTime_in_secs": 3465,
    "timestamp": "2026-04-16T16:24:41.167814091Z"
  },
  "File: Charge_Summary_Data_sidis_epip_richcap.inb.qa.new8.nSidis_005237.hipo.json": {
    "input_file": "nSidis_005237.hipo",
    "output_root": "Data_sidis_epip_richcap.inb.qa.new8.nSidis_005237.hipo.root",
    "accumulated_charge": 155998.661235,
    "total_events": 1264378,
    "events_after_PID_Cuts": 732894,
    "Pass_1_PID_Cut_events": 885730,
    "Multiple_Pions_Per_event": 162834,
    "RunTime_in_secs": 3839,
    "timestamp": "2026-04-16T16:33:24.129422171Z"
  },
  "File: Charge_Summary_Data_sidis_epip_richcap.inb.qa.new8.nSidis_005238.hipo.json": {
    "input_file": "nSidis_005238.hipo",
    "output_root": "Data_sidis_epip_richcap.inb.qa.new8.nSidis_005238.hipo.root",
    "accumulated_charge": 315191.62801000004,
    "total_events": 2553413,
    "events_after_PID_Cuts": 1483538,
    "Pass_1_PID_Cut_events": 1791808,
    "Multiple_Pions_Per_event": 327031,
    "RunTime_in_secs": 7466,
    "timestamp": "2026-04-16T18:10:23.268948489Z"
  },
  "File: Charge_Summary_Data_sidis_epip_richcap.inb.qa.new8.nSidis_005239.hipo.json": {
    "input_file": "nSidis_005239.hipo",
    "output_root": "Data_sidis_epip_richcap.inb.qa.new8.nSidis_005239.hipo.root",
    "accumulated_charge": 249280.83361799998,
    "total_events": 2022009,
    "events_after_PID_Cuts": 1190309,
    "Pass_1_PID_Cut_events": 1433215,
    "Multiple_Pions_Per_event": 258323,
    "RunTime_in_secs": 5642,
    "timestamp": "2026-04-16T17:58:48.366516143Z"
  },
  "File: Charge_Summary_Data_sidis_epip_richcap.inb.qa.new8.nSidis_005247.hipo.json": {
    "input_file": "nSidis_005247.hipo",
    "output_root": "Data_sidis_epip_richcap.inb.qa.new8.nSidis_005247.hipo.root",
    "accumulated_charge": 78398.2866,
    "total_events": 636132,
    "events_after_PID_Cuts": 366927,
    "Pass_1_PID_Cut_events": 444924,
    "Multiple_Pions_Per_event": 81487,
    "RunTime_in_secs": 1971,
    "timestamp": "2026-04-16T17:06:20.909970991Z"
  },
  "File: Charge_Summary_Data_sidis_epip_richcap.inb.qa.new8.nSidis_005248.hipo.json": {
    "input_file": "nSidis_005248.hipo",
    "output_root": "Data_sidis_epip_richcap.inb.qa.new8.nSidis_005248.hipo.root",
    "accumulated_charge": 401741.0402,
    "total_events": 3246998,
    "events_after_PID_Cuts": 1877877,
    "Pass_1_PID_Cut_events": 2273463,
    "Multiple_Pions_Per_event": 417130,
    "RunTime_in_secs": 9256,
    "timestamp": "2026-04-16T19:13:05.144542527Z"
  },
  "File: Charge_Summary_Data_sidis_epip_richcap.inb.qa.new8.nSidis_005249.hipo.json": {
    "input_file": "nSidis_005249.hipo",
    "output_root": "Data_sidis_epip_richcap.inb.qa.new8.nSidis_005249.hipo.root",
    "accumulated_charge": 403586.59094599995,
    "total_events": 3259672,
    "events_after_PID_Cuts": 1888064,
    "Pass_1_PID_Cut_events": 2281717,
    "Multiple_Pions_Per_event": 417776,
    "RunTime_in_secs": 9106,
    "timestamp": "2026-04-16T19:12:54.938244673Z"
  },
  "File: Charge_Summary_Data_sidis_epip_richcap.inb.qa.new8.nSidis_005250.hipo.json": {
    "input_file": "nSidis_005250.hipo",
    "output_root": "Data_sidis_epip_richcap.inb.qa.new8.nSidis_005250.hipo.root",
    "accumulated_charge": 0.0,
    "total_events": 0,
    "events_after_PID_Cuts": 0,
    "Pass_1_PID_Cut_events": 0,
    "Multiple_Pions_Per_event": 0,
    "RunTime_in_secs": 54,
    "timestamp": "2026-04-16T17:07:19.251135655Z"
  },
  "File: Charge_Summary_Data_sidis_epip_richcap.inb.qa.new8.nSidis_005252.hipo.json": {
    "input_file": "nSidis_005252.hipo",
    "output_root": "Data_sidis_epip_richcap.inb.qa.new8.nSidis_005252.hipo.root",
    "accumulated_charge": 248739.69664399998,
    "total_events": 2012333,
    "events_after_PID_Cuts": 1163008,
    "Pass_1_PID_Cut_events": 1406687,
    "Multiple_Pions_Per_event": 258513,
    "RunTime_in_secs": 5658,
    "timestamp": "2026-04-16T18:41:40.802618940Z"
  },
  "File: Charge_Summary_Data_sidis_epip_richcap.inb.qa.new8.nSidis_005253.hipo.json": {
    "input_file": "nSidis_005253.hipo",
    "output_root": "Data_sidis_epip_richcap.inb.qa.new8.nSidis_005253.hipo.root",
    "accumulated_charge": 91173.86638400001,
    "total_events": 737141,
    "events_after_PID_Cuts": 427386,
    "Pass_1_PID_Cut_events": 516633,
    "Multiple_Pions_Per_event": 95194,
    "RunTime_in_secs": 2132,
    "timestamp": "2026-04-16T17:56:35.637192655Z"
  },
  "File: Charge_Summary_Data_sidis_epip_richcap.inb.qa.new8.nSidis_005257.hipo.json": {
    "input_file": "nSidis_005257.hipo",
    "output_root": "Data_sidis_epip_richcap.inb.qa.new8.nSidis_005257.hipo.root",
    "accumulated_charge": 399906.65888999996,
    "total_events": 3233992,
    "events_after_PID_Cuts": 1873907,
    "Pass_1_PID_Cut_events": 2264657,
    "Multiple_Pions_Per_event": 416376,
    "RunTime_in_secs": 9882,
    "timestamp": "2026-04-16T20:17:57.543570573Z"
  },
  "File: Charge_Summary_Data_sidis_epip_richcap.inb.qa.new8.nSidis_005258.hipo.json": {
    "input_file": "nSidis_005258.hipo",
    "output_root": "Data_sidis_epip_richcap.inb.qa.new8.nSidis_005258.hipo.root",
    "accumulated_charge": 399967.261126,
    "total_events": 3233673,
    "events_after_PID_Cuts": 1871507,
    "Pass_1_PID_Cut_events": 2262859,
    "Multiple_Pions_Per_event": 416646,
    "RunTime_in_secs": 10402,
    "timestamp": "2026-04-16T20:50:01.695544460Z"
  },
  "File: Charge_Summary_Data_sidis_epip_richcap.inb.qa.new8.nSidis_005259.hipo.json": {
    "input_file": "nSidis_005259.hipo",
    "output_root": "Data_sidis_epip_richcap.inb.qa.new8.nSidis_005259.hipo.root",
    "accumulated_charge": 150999.8199,
    "total_events": 1223449,
    "events_after_PID_Cuts": 709552,
    "Pass_1_PID_Cut_events": 857062,
    "Multiple_Pions_Per_event": 157468,
    "RunTime_in_secs": 3418,
    "timestamp": "2026-04-16T18:55:50.590953069Z"
  },
  "File: Charge_Summary_Data_sidis_epip_richcap.inb.qa.new8.nSidis_005261.hipo.json": {
    "input_file": "nSidis_005261.hipo",
    "output_root": "Data_sidis_epip_richcap.inb.qa.new8.nSidis_005261.hipo.root",
    "accumulated_charge": 401689.89052499994,
    "total_events": 3247371,
    "events_after_PID_Cuts": 1880586,
    "Pass_1_PID_Cut_events": 2272224,
    "Multiple_Pions_Per_event": 417510,
    "RunTime_in_secs": 9234,
    "timestamp": "2026-04-16T20:44:22.258054018Z"
  },
  "File: Charge_Summary_Data_sidis_epip_richcap.inb.qa.new8.nSidis_005262.hipo.json": {
    "input_file": "nSidis_005262.hipo",
    "output_root": "Data_sidis_epip_richcap.inb.qa.new8.nSidis_005262.hipo.root",
    "accumulated_charge": 184254.2856,
    "total_events": 1486082,
    "events_after_PID_Cuts": 861052,
    "Pass_1_PID_Cut_events": 1041328,
    "Multiple_Pions_Per_event": 190104,
    "RunTime_in_secs": 5015,
    "timestamp": "2026-04-16T20:05:20.638504387Z"
  },
  "File: Charge_Summary_Data_sidis_epip_richcap.inb.qa.new8.nSidis_005300.hipo.json": {
    "input_file": "nSidis_005300.hipo",
    "output_root": "Data_sidis_epip_richcap.inb.qa.new8.nSidis_005300.hipo.root",
    "accumulated_charge": 0.0,
    "total_events": 0,
    "events_after_PID_Cuts": 0,
    "Pass_1_PID_Cut_events": 0,
    "Multiple_Pions_Per_event": 0,
    "RunTime_in_secs": 31,
    "timestamp": "2026-04-16T18:56:25.680192451Z"
  },
  "File: Charge_Summary_Data_sidis_epip_richcap.inb.qa.new8.nSidis_005301.hipo.json": {
    "input_file": "nSidis_005301.hipo",
    "output_root": "Data_sidis_epip_richcap.inb.qa.new8.nSidis_005301.hipo.root",
    "accumulated_charge": 0.0,
    "total_events": 0,
    "events_after_PID_Cuts": 0,
    "Pass_1_PID_Cut_events": 0,
    "Multiple_Pions_Per_event": 0,
    "RunTime_in_secs": 36,
    "timestamp": "2026-04-16T18:57:05.934503809Z"
  },
  "File: Charge_Summary_Data_sidis_epip_richcap.inb.qa.new8.nSidis_005302.hipo.json": {
    "input_file": "nSidis_005302.hipo",
    "output_root": "Data_sidis_epip_richcap.inb.qa.new8.nSidis_005302.hipo.root",
    "accumulated_charge": 0.0,
    "total_events": 0,
    "events_after_PID_Cuts": 0,
    "Pass_1_PID_Cut_events": 0,
    "Multiple_Pions_Per_event": 0,
    "RunTime_in_secs": 45,
    "timestamp": "2026-04-16T18:57:54.733413493Z"
  },
  "File: Charge_Summary_Data_sidis_epip_richcap.inb.qa.new8.nSidis_005303.hipo.json": {
    "input_file": "nSidis_005303.hipo",
    "output_root": "Data_sidis_epip_richcap.inb.qa.new8.nSidis_005303.hipo.root",
    "accumulated_charge": 390527.05562999996,
    "total_events": 3175121,
    "events_after_PID_Cuts": 1835610,
    "Pass_1_PID_Cut_events": 2219549,
    "Multiple_Pions_Per_event": 409198,
    "RunTime_in_secs": 12595,
    "timestamp": "2026-04-16T22:27:53.970950721Z"
  },
  "File: Charge_Summary_Data_sidis_epip_richcap.inb.qa.new8.nSidis_005304.hipo.json": {
    "input_file": "nSidis_005304.hipo",
    "output_root": "Data_sidis_epip_richcap.inb.qa.new8.nSidis_005304.hipo.root",
    "accumulated_charge": 376063.20736,
    "total_events": 3064655,
    "events_after_PID_Cuts": 1770144,
    "Pass_1_PID_Cut_events": 2141249,
    "Multiple_Pions_Per_event": 395848,
    "RunTime_in_secs": 10313,
    "timestamp": "2026-04-16T22:04:53.605226830Z"
  },
  "File: Charge_Summary_Data_sidis_epip_richcap.inb.qa.new8.nSidis_005305.hipo.json": {
    "input_file": "nSidis_005305.hipo",
    "output_root": "Data_sidis_epip_richcap.inb.qa.new8.nSidis_005305.hipo.root",
    "accumulated_charge": 145599.74129,
    "total_events": 1184482,
    "events_after_PID_Cuts": 684441,
    "Pass_1_PID_Cut_events": 827538,
    "Multiple_Pions_Per_event": 151962,
    "RunTime_in_secs": 4866,
    "timestamp": "2026-04-16T20:36:19.716830933Z"
  },
  "File: Charge_Summary_Data_sidis_epip_richcap.inb.qa.new8.nSidis_005306.hipo.json": {
    "input_file": "nSidis_005306.hipo",
    "output_root": "Data_sidis_epip_richcap.inb.qa.new8.nSidis_005306.hipo.root",
    "accumulated_charge": 373214.26660000003,
    "total_events": 3042501,
    "events_after_PID_Cuts": 1761465,
    "Pass_1_PID_Cut_events": 2129615,
    "Multiple_Pions_Per_event": 391104,
    "RunTime_in_secs": 10297,
    "timestamp": "2026-04-16T22:57:02.284354188Z"
  },
  "File: Charge_Summary_Data_sidis_epip_richcap.inb.qa.new8.nSidis_005307.hipo.json": {
    "input_file": "nSidis_005307.hipo",
    "output_root": "Data_sidis_epip_richcap.inb.qa.new8.nSidis_005307.hipo.root",
    "accumulated_charge": 44172.34185999999,
    "total_events": 359128,
    "events_after_PID_Cuts": 207681,
    "Pass_1_PID_Cut_events": 251421,
    "Multiple_Pions_Per_event": 46463,
    "RunTime_in_secs": 1540,
    "timestamp": "2026-04-16T20:43:42.744449748Z"
  },
  "File: Charge_Summary_Data_sidis_epip_richcap.inb.qa.new8.nSidis_005310.hipo.json": {
    "input_file": "nSidis_005310.hipo",
    "output_root": "Data_sidis_epip_richcap.inb.qa.new8.nSidis_005310.hipo.root",
    "accumulated_charge": 97098.01498,
    "total_events": 788124,
    "events_after_PID_Cuts": 456278,
    "Pass_1_PID_Cut_events": 551660,
    "Multiple_Pions_Per_event": 101162,
    "RunTime_in_secs": 2358,
    "timestamp": "2026-04-16T21:15:42.265703659Z"
  },
  "File: Charge_Summary_Data_sidis_epip_richcap.inb.qa.new8.nSidis_005311.hipo.json": {
    "input_file": "nSidis_005311.hipo",
    "output_root": "Data_sidis_epip_richcap.inb.qa.new8.nSidis_005311.hipo.root",
    "accumulated_charge": 128559.20449,
    "total_events": 1043600,
    "events_after_PID_Cuts": 604032,
    "Pass_1_PID_Cut_events": 730376,
    "Multiple_Pions_Per_event": 133952,
    "RunTime_in_secs": 3432,
    "timestamp": "2026-04-16T21:40:59.425521880Z"
  },
  "File: Charge_Summary_Data_sidis_epip_richcap.inb.qa.new8.nSidis_005315.hipo.json": {
    "input_file": "nSidis_005315.hipo",
    "output_root": "Data_sidis_epip_richcap.inb.qa.new8.nSidis_005315.hipo.root",
    "accumulated_charge": 89998.70509,
    "total_events": 730597,
    "events_after_PID_Cuts": 422017,
    "Pass_1_PID_Cut_events": 510658,
    "Multiple_Pions_Per_event": 94423,
    "RunTime_in_secs": 2255,
    "timestamp": "2026-04-16T21:22:02.600019553Z"
  },
  "File: Charge_Summary_Data_sidis_epip_richcap.inb.qa.new8.nSidis_005316.hipo.json": {
    "input_file": "nSidis_005316.hipo",
    "output_root": "Data_sidis_epip_richcap.inb.qa.new8.nSidis_005316.hipo.root",
    "accumulated_charge": 0.0,
    "total_events": 0,
    "events_after_PID_Cuts": 0,
    "Pass_1_PID_Cut_events": 0,
    "Multiple_Pions_Per_event": 0,
    "RunTime_in_secs": 33,
    "timestamp": "2026-04-16T20:50:40.392441734Z"
  },
  "File: Charge_Summary_Data_sidis_epip_richcap.inb.qa.new8.nSidis_005317.hipo.json": {
    "input_file": "nSidis_005317.hipo",
    "output_root": "Data_sidis_epip_richcap.inb.qa.new8.nSidis_005317.hipo.root",
    "accumulated_charge": 373598.09268,
    "total_events": 3030747,
    "events_after_PID_Cuts": 1752477,
    "Pass_1_PID_Cut_events": 2117854,
    "Multiple_Pions_Per_event": 389676,
    "RunTime_in_secs": 10906,
    "timestamp": "2026-04-16T23:52:30.134377629Z"
  },
  "File: Charge_Summary_Data_sidis_epip_richcap.inb.qa.new8.nSidis_005318.hipo.json": {
    "input_file": "nSidis_005318.hipo",
    "output_root": "Data_sidis_epip_richcap.inb.qa.new8.nSidis_005318.hipo.root",
    "accumulated_charge": 374199.71102,
    "total_events": 3036879,
    "events_after_PID_Cuts": 1756522,
    "Pass_1_PID_Cut_events": 2123436,
    "Multiple_Pions_Per_event": 389959,
    "RunTime_in_secs": 11356,
    "timestamp": "2026-04-17T00:25:02.178633433Z"
  },
  "File: Charge_Summary_Data_sidis_epip_richcap.inb.qa.new8.nSidis_005319.hipo.json": {
    "input_file": "nSidis_005319.hipo",
    "output_root": "Data_sidis_epip_richcap.inb.qa.new8.nSidis_005319.hipo.root",
    "accumulated_charge": 379263.9707,
    "total_events": 3068124,
    "events_after_PID_Cuts": 1774940,
    "Pass_1_PID_Cut_events": 2146914,
    "Multiple_Pions_Per_event": 393933,
    "RunTime_in_secs": 10765,
    "timestamp": "2026-04-17T00:21:32.055314986Z"
  },
  "File: Charge_Summary_Data_sidis_epip_richcap.inb.qa.new8.nSidis_005320.hipo.json": {
    "input_file": "nSidis_005320.hipo",
    "output_root": "Data_sidis_epip_richcap.inb.qa.new8.nSidis_005320.hipo.root",
    "accumulated_charge": 186600.40671,
    "total_events": 1512906,
    "events_after_PID_Cuts": 876210,
    "Pass_1_PID_Cut_events": 1059691,
    "Multiple_Pions_Per_event": 194703,
    "RunTime_in_secs": 5619,
    "timestamp": "2026-04-16T23:14:43.607164207Z"
  },
  "File: Charge_Summary_Data_sidis_epip_richcap.inb.qa.new8.nSidis_005323.hipo.json": {
    "input_file": "nSidis_005323.hipo",
    "output_root": "Data_sidis_epip_richcap.inb.qa.new8.nSidis_005323.hipo.root",
    "accumulated_charge": 24507.161579999996,
    "total_events": 198979,
    "events_after_PID_Cuts": 115055,
    "Pass_1_PID_Cut_events": 139119,
    "Multiple_Pions_Per_event": 25467,
    "RunTime_in_secs": 762,
    "timestamp": "2026-04-16T22:17:42.732439994Z"
  },
  "File: Charge_Summary_Data_sidis_epip_richcap.inb.qa.new8.nSidis_005324.hipo.json": {
    "input_file": "nSidis_005324.hipo",
    "output_root": "Data_sidis_epip_richcap.inb.qa.new8.nSidis_005324.hipo.root",
    "accumulated_charge": 31133.372,
    "total_events": 253394,
    "events_after_PID_Cuts": 146422,
    "Pass_1_PID_Cut_events": 177469,
    "Multiple_Pions_Per_event": 32587,
    "RunTime_in_secs": 973,
    "timestamp": "2026-04-16T22:34:00.422442381Z"
  },
  "File: Charge_Summary_Data_sidis_epip_richcap.inb.qa.new8.nSidis_005325.hipo.json": {
    "input_file": "nSidis_005325.hipo",
    "output_root": "Data_sidis_epip_richcap.inb.qa.new8.nSidis_005325.hipo.root",
    "accumulated_charge": 0.0,
    "total_events": 0,
    "events_after_PID_Cuts": 0,
    "Pass_1_PID_Cut_events": 0,
    "Multiple_Pions_Per_event": 0,
    "RunTime_in_secs": 31,
    "timestamp": "2026-04-16T22:28:30.957453283Z"
  },
  "File: Charge_Summary_Data_sidis_epip_richcap.inb.qa.new8.nSidis_005333.hipo.json": {
    "input_file": "nSidis_005333.hipo",
    "output_root": "Data_sidis_epip_richcap.inb.qa.new8.nSidis_005333.hipo.root",
    "accumulated_charge": 91527.27794000001,
    "total_events": 749578,
    "events_after_PID_Cuts": 434493,
    "Pass_1_PID_Cut_events": 529650,
    "Multiple_Pions_Per_event": 94971,
    "RunTime_in_secs": 2500,
    "timestamp": "2026-04-16T23:10:16.066082030Z"
  },
  "File: Charge_Summary_Data_sidis_epip_richcap.inb.qa.new8.nSidis_005334.hipo.json": {
    "input_file": "nSidis_005334.hipo",
    "output_root": "Data_sidis_epip_richcap.inb.qa.new8.nSidis_005334.hipo.root",
    "accumulated_charge": 66992.00875000001,
    "total_events": 548363,
    "events_after_PID_Cuts": 319415,
    "Pass_1_PID_Cut_events": 388154,
    "Multiple_Pions_Per_event": 69431,
    "RunTime_in_secs": 1944,
    "timestamp": "2026-04-16T23:06:29.211995957Z"
  },
  "File: Charge_Summary_Data_sidis_epip_richcap.inb.qa.new8.nSidis_005335.hipo.json": {
    "input_file": "nSidis_005335.hipo",
    "output_root": "Data_sidis_epip_richcap.inb.qa.new8.nSidis_005335.hipo.root",
    "accumulated_charge": 13040.146990000001,
    "total_events": 103954,
    "events_after_PID_Cuts": 60623,
    "Pass_1_PID_Cut_events": 73756,
    "Multiple_Pions_Per_event": 12939,
    "RunTime_in_secs": 403,
    "timestamp": "2026-04-16T23:03:51.025327091Z"
  },
  "File: Charge_Summary_Data_sidis_epip_richcap.inb.qa.new8.nSidis_005336.hipo.json": {
    "input_file": "nSidis_005336.hipo",
    "output_root": "Data_sidis_epip_richcap.inb.qa.new8.nSidis_005336.hipo.root",
    "accumulated_charge": 8781.580506000002,
    "total_events": 69084,
    "events_after_PID_Cuts": 39906,
    "Pass_1_PID_Cut_events": 48600,
    "Multiple_Pions_Per_event": 8360,
    "RunTime_in_secs": 263,
    "timestamp": "2026-04-16T23:08:18.860823703Z"
  },
  "File: Charge_Summary_Data_sidis_epip_richcap.inb.qa.new8.nSidis_005339.hipo.json": {
    "input_file": "nSidis_005339.hipo",
    "output_root": "Data_sidis_epip_richcap.inb.qa.new8.nSidis_005339.hipo.root",
    "accumulated_charge": 88032.8809,
    "total_events": 719584,
    "events_after_PID_Cuts": 418900,
    "Pass_1_PID_Cut_events": 509138,
    "Multiple_Pions_Per_event": 91617,
    "RunTime_in_secs": 2975,
    "timestamp": "2026-04-16T23:56:10.432711899Z"
  },
  "File: Charge_Summary_Data_sidis_epip_richcap.inb.qa.new8.nSidis_005340.hipo.json": {
    "input_file": "nSidis_005340.hipo",
    "output_root": "Data_sidis_epip_richcap.inb.qa.new8.nSidis_005340.hipo.root",
    "accumulated_charge": 37238.6225,
    "total_events": 303406,
    "events_after_PID_Cuts": 176494,
    "Pass_1_PID_Cut_events": 214605,
    "Multiple_Pions_Per_event": 38736,
    "RunTime_in_secs": 1217,
    "timestamp": "2026-04-16T23:28:41.254102846Z"
  },
  "File: Charge_Summary_Data_sidis_epip_richcap.inb.qa.new8.nSidis_005341.hipo.json": {
    "input_file": "nSidis_005341.hipo",
    "output_root": "Data_sidis_epip_richcap.inb.qa.new8.nSidis_005341.hipo.root",
    "accumulated_charge": 121502.51686,
    "total_events": 978446,
    "events_after_PID_Cuts": 571968,
    "Pass_1_PID_Cut_events": 693803,
    "Multiple_Pions_Per_event": 124730,
    "RunTime_in_secs": 3846,
    "timestamp": "2026-04-17T00:14:27.382873164Z"
  },
  "File: Charge_Summary_Data_sidis_epip_richcap.inb.qa.new8.nSidis_005342.hipo.json": {
    "input_file": "nSidis_005342.hipo",
    "output_root": "Data_sidis_epip_richcap.inb.qa.new8.nSidis_005342.hipo.root",
    "accumulated_charge": 116117.37827,
    "total_events": 943589,
    "events_after_PID_Cuts": 543311,
    "Pass_1_PID_Cut_events": 662152,
    "Multiple_Pions_Per_event": 120897,
    "RunTime_in_secs": 3747,
    "timestamp": "2026-04-17T00:17:16.714575353Z"
  },
  "File: Charge_Summary_Data_sidis_epip_richcap.inb.qa.new8.nSidis_005343.hipo.json": {
    "input_file": "nSidis_005343.hipo",
    "output_root": "Data_sidis_epip_richcap.inb.qa.new8.nSidis_005343.hipo.root",
    "accumulated_charge": 59859.81529,
    "total_events": 487403,
    "events_after_PID_Cuts": 282193,
    "Pass_1_PID_Cut_events": 343136,
    "Multiple_Pions_Per_event": 62275,
    "RunTime_in_secs": 2003,
    "timestamp": "2026-04-17T00:02:10.908466785Z"
  },
  "File: Charge_Summary_Data_sidis_epip_richcap.inb.qa.new8.nSidis_005344.hipo.json": {
    "input_file": "nSidis_005344.hipo",
    "output_root": "Data_sidis_epip_richcap.inb.qa.new8.nSidis_005344.hipo.root",
    "accumulated_charge": 152440.0404,
    "total_events": 1251797,
    "events_after_PID_Cuts": 738773,
    "Pass_1_PID_Cut_events": 893711,
    "Multiple_Pions_Per_event": 158342,
    "RunTime_in_secs": 4204,
    "timestamp": "2026-04-17T01:02:40.482629494Z"
  },
  "File: Charge_Summary_Data_sidis_epip_richcap.inb.qa.new8.nSidis_005345.hipo.json": {
    "input_file": "nSidis_005345.hipo",
    "output_root": "Data_sidis_epip_richcap.inb.qa.new8.nSidis_005345.hipo.root",
    "accumulated_charge": 379590.55523000006,
    "total_events": 3086953,
    "events_after_PID_Cuts": 1794813,
    "Pass_1_PID_Cut_events": 2178193,
    "Multiple_Pions_Per_event": 394165,
    "RunTime_in_secs": 10556,
    "timestamp": "2026-04-17T02:52:12.486393802Z"
  },
  "File: Charge_Summary_Data_sidis_epip_richcap.inb.qa.new8.nSidis_005346.hipo.json": {
    "input_file": "nSidis_005346.hipo",
    "output_root": "Data_sidis_epip_richcap.inb.qa.new8.nSidis_005346.hipo.root",
    "accumulated_charge": 381441.76326000004,
    "total_events": 3108479,
    "events_after_PID_Cuts": 1799938,
    "Pass_1_PID_Cut_events": 2186456,
    "Multiple_Pions_Per_event": 397478,
    "RunTime_in_secs": 10263,
    "timestamp": "2026-04-17T02:53:19.378404095Z"
  },
  "File: Charge_Summary_Data_sidis_epip_richcap.inb.qa.new8.nSidis_005347.hipo.json": {
    "input_file": "nSidis_005347.hipo",
    "output_root": "Data_sidis_epip_richcap.inb.qa.new8.nSidis_005347.hipo.root",
    "accumulated_charge": 179006.51604,
    "total_events": 1404610,
    "events_after_PID_Cuts": 812914,
    "Pass_1_PID_Cut_events": 987722,
    "Multiple_Pions_Per_event": 175407,
    "RunTime_in_secs": 5073,
    "timestamp": "2026-04-17T01:39:05.927168108Z"
  },
  "File: Charge_Summary_Data_sidis_epip_richcap.inb.qa.new8.nSidis_005349.hipo.json": {
    "input_file": "nSidis_005349.hipo",
    "output_root": "Data_sidis_epip_richcap.inb.qa.new8.nSidis_005349.hipo.root",
    "accumulated_charge": 240445.52943999998,
    "total_events": 1949493,
    "events_after_PID_Cuts": 1130018,
    "Pass_1_PID_Cut_events": 1372246,
    "Multiple_Pions_Per_event": 249381,
    "RunTime_in_secs": 6371,
    "timestamp": "2026-04-17T02:03:34.199369124Z"
  },
  "File: Charge_Summary_Data_sidis_epip_richcap.inb.qa.new8.nSidis_005351.hipo.json": {
    "input_file": "nSidis_005351.hipo",
    "output_root": "Data_sidis_epip_richcap.inb.qa.new8.nSidis_005351.hipo.root",
    "accumulated_charge": 52497.565243000005,
    "total_events": 427804,
    "events_after_PID_Cuts": 247761,
    "Pass_1_PID_Cut_events": 301141,
    "Multiple_Pions_Per_event": 54944,
    "RunTime_in_secs": 1497,
    "timestamp": "2026-04-17T00:46:36.267847108Z"
  },
  "File: Charge_Summary_Data_sidis_epip_richcap.inb.qa.new8.nSidis_005354.hipo.json": {
    "input_file": "nSidis_005354.hipo",
    "output_root": "Data_sidis_epip_richcap.inb.qa.new8.nSidis_005354.hipo.root",
    "accumulated_charge": 379301.03118,
    "total_events": 3086681,
    "events_after_PID_Cuts": 1788403,
    "Pass_1_PID_Cut_events": 2170681,
    "Multiple_Pions_Per_event": 394606,
    "RunTime_in_secs": 10247,
    "timestamp": "2026-04-17T03:15:54.754674189Z"
  },
  "File: Charge_Summary_Data_sidis_epip_richcap.inb.qa.new8.nSidis_005355.hipo.json": {
    "input_file": "nSidis_005355.hipo",
    "output_root": "Data_sidis_epip_richcap.inb.qa.new8.nSidis_005355.hipo.root",
    "accumulated_charge": 170209.22787,
    "total_events": 1383063,
    "events_after_PID_Cuts": 800597,
    "Pass_1_PID_Cut_events": 972849,
    "Multiple_Pions_Per_event": 177195,
    "RunTime_in_secs": 4578,
    "timestamp": "2026-04-17T02:02:59.065084044Z"
  },
  "File: Charge_Summary_Data_sidis_epip_richcap.inb.qa.new8.nSidis_005356.hipo.json": {
    "input_file": "nSidis_005356.hipo",
    "output_root": "Data_sidis_epip_richcap.inb.qa.new8.nSidis_005356.hipo.root",
    "accumulated_charge": 376847.45931000006,
    "total_events": 3018866,
    "events_after_PID_Cuts": 1733040,
    "Pass_1_PID_Cut_events": 2108074,
    "Multiple_Pions_Per_event": 384103,
    "RunTime_in_secs": 9372,
    "timestamp": "2026-04-17T03:38:56.751258566Z"
  },
  "File: Charge_Summary_Data_sidis_epip_richcap.inb.qa.new8.nSidis_005357.hipo.json": {
    "input_file": "nSidis_005357.hipo",
    "output_root": "Data_sidis_epip_richcap.inb.qa.new8.nSidis_005357.hipo.root",
    "accumulated_charge": 376874.5153900001,
    "total_events": 3040596,
    "events_after_PID_Cuts": 1747183,
    "Pass_1_PID_Cut_events": 2126022,
    "Multiple_Pions_Per_event": 390745,
    "RunTime_in_secs": 9972,
    "timestamp": "2026-04-17T04:25:22.365451307Z"
  },
  "File: Charge_Summary_Data_sidis_epip_richcap.inb.qa.new8.nSidis_005358.hipo.json": {
    "input_file": "nSidis_005358.hipo",
    "output_root": "Data_sidis_epip_richcap.inb.qa.new8.nSidis_005358.hipo.root",
    "accumulated_charge": 382812.77922,
    "total_events": 3080177,
    "events_after_PID_Cuts": 1769389,
    "Pass_1_PID_Cut_events": 2151189,
    "Multiple_Pions_Per_event": 396202,
    "RunTime_in_secs": 9776,
    "timestamp": "2026-04-17T04:45:59.947241213Z"
  },
  "File: Charge_Summary_Data_sidis_epip_richcap.inb.qa.new8.nSidis_005359.hipo.json": {
    "input_file": "nSidis_005359.hipo",
    "output_root": "Data_sidis_epip_richcap.inb.qa.new8.nSidis_005359.hipo.root",
    "accumulated_charge": 381920.20081,
    "total_events": 3079700,
    "events_after_PID_Cuts": 1768669,
    "Pass_1_PID_Cut_events": 2151316,
    "Multiple_Pions_Per_event": 395762,
    "RunTime_in_secs": 9587,
    "timestamp": "2026-04-17T04:43:25.591590683Z"
  },
  "File: Charge_Summary_Data_sidis_epip_richcap.inb.qa.new8.nSidis_005360.hipo.json": {
    "input_file": "nSidis_005360.hipo",
    "output_root": "Data_sidis_epip_richcap.inb.qa.new8.nSidis_005360.hipo.root",
    "accumulated_charge": 379021.30027,
    "total_events": 3053098,
    "events_after_PID_Cuts": 1754889,
    "Pass_1_PID_Cut_events": 2133832,
    "Multiple_Pions_Per_event": 391190,
    "RunTime_in_secs": 9526,
    "timestamp": "2026-04-17T05:31:03.058627251Z"
  },
  "File: Charge_Summary_Data_sidis_epip_richcap.inb.qa.new8.nSidis_005361.hipo.json": {
    "input_file": "nSidis_005361.hipo",
    "output_root": "Data_sidis_epip_richcap.inb.qa.new8.nSidis_005361.hipo.root",
    "accumulated_charge": 373889.33797,
    "total_events": 3016137,
    "events_after_PID_Cuts": 1735854,
    "Pass_1_PID_Cut_events": 2109520,
    "Multiple_Pions_Per_event": 387411,
    "RunTime_in_secs": 9317,
    "timestamp": "2026-04-17T05:28:40.750171888Z"
  },
  "File: Charge_Summary_Data_sidis_epip_richcap.inb.qa.new8.nSidis_005362.hipo.json": {
    "input_file": "nSidis_005362.hipo",
    "output_root": "Data_sidis_epip_richcap.inb.qa.new8.nSidis_005362.hipo.root",
    "accumulated_charge": 26530.823075999997,
    "total_events": 215649,
    "events_after_PID_Cuts": 124111,
    "Pass_1_PID_Cut_events": 151221,
    "Multiple_Pions_Per_event": 27579,
    "RunTime_in_secs": 695,
    "timestamp": "2026-04-17T03:27:33.860583772Z"
  },
  "File: Charge_Summary_Data_sidis_epip_richcap.inb.qa.new8.nSidis_005366.hipo.json": {
    "input_file": "nSidis_005366.hipo",
    "output_root": "Data_sidis_epip_richcap.inb.qa.new8.nSidis_005366.hipo.root",
    "accumulated_charge": 393405.15210999997,
    "total_events": 3191760,
    "events_after_PID_Cuts": 1840652,
    "Pass_1_PID_Cut_events": 2238318,
    "Multiple_Pions_Per_event": 409613,
    "RunTime_in_secs": 9545,
    "timestamp": "2026-04-17T06:06:43.622807052Z"
  },
  "File: Charge_Summary_Data_sidis_epip_richcap.inb.qa.new8.nSidis_005367.hipo.json": {
    "input_file": "nSidis_005367.hipo",
    "output_root": "Data_sidis_epip_richcap.inb.qa.new8.nSidis_005367.hipo.root",
    "accumulated_charge": 373672.7373,
    "total_events": 3016770,
    "events_after_PID_Cuts": 1724533,
    "Pass_1_PID_Cut_events": 2100111,
    "Multiple_Pions_Per_event": 388253,
    "RunTime_in_secs": 9084,
    "timestamp": "2026-04-17T06:10:24.881388896Z"
  },
  "File: Charge_Summary_Data_sidis_epip_richcap.inb.qa.new8.nSidis_005368.hipo.json": {
    "input_file": "nSidis_005368.hipo",
    "output_root": "Data_sidis_epip_richcap.inb.qa.new8.nSidis_005368.hipo.root",
    "accumulated_charge": 327086.45339999994,
    "total_events": 2634489,
    "events_after_PID_Cuts": 1505817,
    "Pass_1_PID_Cut_events": 1832857,
    "Multiple_Pions_Per_event": 339346,
    "RunTime_in_secs": 7518,
    "timestamp": "2026-04-17T06:30:45.863560546Z"
  },
  "File: Charge_Summary_Data_sidis_epip_richcap.inb.qa.new8.nSidis_005369.hipo.json": {
    "input_file": "nSidis_005369.hipo",
    "output_root": "Data_sidis_epip_richcap.inb.qa.new8.nSidis_005369.hipo.root",
    "accumulated_charge": 94483.90827,
    "total_events": 763077,
    "events_after_PID_Cuts": 435454,
    "Pass_1_PID_Cut_events": 530984,
    "Multiple_Pions_Per_event": 98499,
    "RunTime_in_secs": 2478,
    "timestamp": "2026-04-17T05:24:46.722472307Z"
  },
  "File: Charge_Summary_Data_sidis_epip_richcap.inb.qa.new8.nSidis_005370.hipo.json": {
    "input_file": "nSidis_005370.hipo",
    "output_root": "Data_sidis_epip_richcap.inb.qa.new8.nSidis_005370.hipo.root",
    "accumulated_charge": 0.0,
    "total_events": 0,
    "events_after_PID_Cuts": 0,
    "Pass_1_PID_Cut_events": 0,
    "Multiple_Pions_Per_event": 0,
    "RunTime_in_secs": 192,
    "timestamp": "2026-04-17T04:49:15.610845137Z"
  },
  "File: Charge_Summary_Data_sidis_epip_richcap.inb.qa.new8.nSidis_005371.hipo.json": {
    "input_file": "nSidis_005371.hipo",
    "output_root": "Data_sidis_epip_richcap.inb.qa.new8.nSidis_005371.hipo.root",
    "accumulated_charge": 0.0,
    "total_events": 0,
    "events_after_PID_Cuts": 0,
    "Pass_1_PID_Cut_events": 0,
    "Multiple_Pions_Per_event": 0,
    "RunTime_in_secs": 12,
    "timestamp": "2026-04-17T04:49:30.991583445Z"
  },
  "File: Charge_Summary_Data_sidis_epip_richcap.inb.qa.new8.nSidis_005372.hipo.json": {
    "input_file": "nSidis_005372.hipo",
    "output_root": "Data_sidis_epip_richcap.inb.qa.new8.nSidis_005372.hipo.root",
    "accumulated_charge": 369374.60867,
    "total_events": 2964853,
    "events_after_PID_Cuts": 1690059,
    "Pass_1_PID_Cut_events": 2058431,
    "Multiple_Pions_Per_event": 382657,
    "RunTime_in_secs": 8613,
    "timestamp": "2026-04-17T07:13:08.482353832Z"
  },
  "File: Charge_Summary_Data_sidis_epip_richcap.inb.qa.new8.nSidis_005373.hipo.json": {
    "input_file": "nSidis_005373.hipo",
    "output_root": "Data_sidis_epip_richcap.inb.qa.new8.nSidis_005373.hipo.root",
    "accumulated_charge": 361562.9060300001,
    "total_events": 2898125,
    "events_after_PID_Cuts": 1652586,
    "Pass_1_PID_Cut_events": 2012268,
    "Multiple_Pions_Per_event": 372963,
    "RunTime_in_secs": 8182,
    "timestamp": "2026-04-17T07:41:13.573188166Z"
  },
  "File: Charge_Summary_Data_sidis_epip_richcap.inb.qa.new8.nSidis_005374.hipo.json": {
    "input_file": "nSidis_005374.hipo",
    "output_root": "Data_sidis_epip_richcap.inb.qa.new8.nSidis_005374.hipo.root",
    "accumulated_charge": 382763.06454,
    "total_events": 3040384,
    "events_after_PID_Cuts": 1731694,
    "Pass_1_PID_Cut_events": 2110779,
    "Multiple_Pions_Per_event": 390882,
    "RunTime_in_secs": 8523,
    "timestamp": "2026-04-17T07:50:48.316253321Z"
  },
  "File: Charge_Summary_Data_sidis_epip_richcap.inb.qa.new8.nSidis_005375.hipo.json": {
    "input_file": "nSidis_005375.hipo",
    "output_root": "Data_sidis_epip_richcap.inb.qa.new8.nSidis_005375.hipo.root",
    "accumulated_charge": 389415.04073999997,
    "total_events": 3086141,
    "events_after_PID_Cuts": 1756552,
    "Pass_1_PID_Cut_events": 2140597,
    "Multiple_Pions_Per_event": 395114,
    "RunTime_in_secs": 8556,
    "timestamp": "2026-04-17T07:53:43.750310521Z"
  },
  "File: Charge_Summary_Data_sidis_epip_richcap.inb.qa.new8.nSidis_005376.hipo.json": {
    "input_file": "nSidis_005376.hipo",
    "output_root": "Data_sidis_epip_richcap.inb.qa.new8.nSidis_005376.hipo.root",
    "accumulated_charge": 290325.12104,
    "total_events": 2322507,
    "events_after_PID_Cuts": 1324072,
    "Pass_1_PID_Cut_events": 1612700,
    "Multiple_Pions_Per_event": 297810,
    "RunTime_in_secs": 6333,
    "timestamp": "2026-04-17T07:52:20.455798272Z"
  },
  "File: Charge_Summary_Data_sidis_epip_richcap.inb.qa.new8.nSidis_005377.hipo.json": {
    "input_file": "nSidis_005377.hipo",
    "output_root": "Data_sidis_epip_richcap.inb.qa.new8.nSidis_005377.hipo.root",
    "accumulated_charge": 0.0,
    "total_events": 0,
    "events_after_PID_Cuts": 0,
    "Pass_1_PID_Cut_events": 0,
    "Multiple_Pions_Per_event": 0,
    "RunTime_in_secs": 10,
    "timestamp": "2026-04-17T06:10:40.033855876Z"
  },
  "File: Charge_Summary_Data_sidis_epip_richcap.inb.qa.new8.nSidis_005378.hipo.json": {
    "input_file": "nSidis_005378.hipo",
    "output_root": "Data_sidis_epip_richcap.inb.qa.new8.nSidis_005378.hipo.root",
    "accumulated_charge": 36987.08995,
    "total_events": 297155,
    "events_after_PID_Cuts": 170200,
    "Pass_1_PID_Cut_events": 207284,
    "Multiple_Pions_Per_event": 38354,
    "RunTime_in_secs": 822,
    "timestamp": "2026-04-17T06:24:26.259187967Z"
  },
  "File: Charge_Summary_Data_sidis_epip_richcap.inb.qa.new8.nSidis_005379.hipo.json": {
    "input_file": "nSidis_005379.hipo",
    "output_root": "Data_sidis_epip_richcap.inb.qa.new8.nSidis_005379.hipo.root",
    "accumulated_charge": 388154.22657000006,
    "total_events": 3100792,
    "events_after_PID_Cuts": 1765179,
    "Pass_1_PID_Cut_events": 2152366,
    "Multiple_Pions_Per_event": 395929,
    "RunTime_in_secs": 8745,
    "timestamp": "2026-04-17T08:50:16.080052928Z"
  },
  "File: Charge_Summary_Data_sidis_epip_richcap.inb.qa.new8.nSidis_005380.hipo.json": {
    "input_file": "nSidis_005380.hipo",
    "output_root": "Data_sidis_epip_richcap.inb.qa.new8.nSidis_005380.hipo.root",
    "accumulated_charge": 357921.90680999996,
    "total_events": 2856274,
    "events_after_PID_Cuts": 1626046,
    "Pass_1_PID_Cut_events": 1982419,
    "Multiple_Pions_Per_event": 363817,
    "RunTime_in_secs": 7996,
    "timestamp": "2026-04-17T08:44:06.457138022Z"
  },
  "File: Charge_Summary_Data_sidis_epip_richcap.inb.qa.new8.nSidis_005381.hipo.json": {
    "input_file": "nSidis_005381.hipo",
    "output_root": "Data_sidis_epip_richcap.inb.qa.new8.nSidis_005381.hipo.root",
    "accumulated_charge": 372224.5875,
    "total_events": 2961591,
    "events_after_PID_Cuts": 1688566,
    "Pass_1_PID_Cut_events": 2057664,
    "Multiple_Pions_Per_event": 376702,
    "RunTime_in_secs": 8048,
    "timestamp": "2026-04-17T09:27:20.358937984Z"
  },
  "File: Charge_Summary_Data_sidis_epip_richcap.inb.qa.new8.nSidis_005382.hipo.json": {
    "input_file": "nSidis_005382.hipo",
    "output_root": "Data_sidis_epip_richcap.inb.qa.new8.nSidis_005382.hipo.root",
    "accumulated_charge": 284980.70674,
    "total_events": 2267873,
    "events_after_PID_Cuts": 1293106,
    "Pass_1_PID_Cut_events": 1574741,
    "Multiple_Pions_Per_event": 288372,
    "RunTime_in_secs": 6180,
    "timestamp": "2026-04-17T09:24:18.123374596Z"
  },
  "File: Charge_Summary_Data_sidis_epip_richcap.inb.qa.new8.nSidis_005383.hipo.json": {
    "input_file": "nSidis_005383.hipo",
    "output_root": "Data_sidis_epip_richcap.inb.qa.new8.nSidis_005383.hipo.root",
    "accumulated_charge": 281844.94205,
    "total_events": 2233221,
    "events_after_PID_Cuts": 1273735,
    "Pass_1_PID_Cut_events": 1552160,
    "Multiple_Pions_Per_event": 284242,
    "RunTime_in_secs": 6043,
    "timestamp": "2026-04-17T09:31:35.257184224Z"
  },
  "File: Charge_Summary_Data_sidis_epip_richcap.inb.qa.new8.nSidis_005386.hipo.json": {
    "input_file": "nSidis_005386.hipo",
    "output_root": "Data_sidis_epip_richcap.inb.qa.new8.nSidis_005386.hipo.root",
    "accumulated_charge": 186787.42651999998,
    "total_events": 1477371,
    "events_after_PID_Cuts": 841118,
    "Pass_1_PID_Cut_events": 1025773,
    "Multiple_Pions_Per_event": 186772,
    "RunTime_in_secs": 4022,
    "timestamp": "2026-04-17T08:59:26.410459314Z"
  },
  "File: Charge_Summary_Data_sidis_epip_richcap.inb.qa.new8.nSidis_005390.hipo.json": {
    "input_file": "nSidis_005390.hipo",
    "output_root": "Data_sidis_epip_richcap.inb.qa.new8.nSidis_005390.hipo.root",
    "accumulated_charge": 0.0,
    "total_events": 0,
    "events_after_PID_Cuts": 0,
    "Pass_1_PID_Cut_events": 0,
    "Multiple_Pions_Per_event": 0,
    "RunTime_in_secs": 12,
    "timestamp": "2026-04-17T07:54:00.068732355Z"
  },
  "File: Charge_Summary_Data_sidis_epip_richcap.inb.qa.new8.nSidis_005391.hipo.json": {
    "input_file": "nSidis_005391.hipo",
    "output_root": "Data_sidis_epip_richcap.inb.qa.new8.nSidis_005391.hipo.root",
    "accumulated_charge": 365195.35440000007,
    "total_events": 2892449,
    "events_after_PID_Cuts": 1657557,
    "Pass_1_PID_Cut_events": 2016888,
    "Multiple_Pions_Per_event": 366412,
    "RunTime_in_secs": 7769,
    "timestamp": "2026-04-17T10:03:32.239602995Z"
  },
  "File: Charge_Summary_Data_sidis_epip_richcap.inb.qa.new8.nSidis_005392.hipo.json": {
    "input_file": "nSidis_005392.hipo",
    "output_root": "Data_sidis_epip_richcap.inb.qa.new8.nSidis_005392.hipo.root",
    "accumulated_charge": 198227.12558999998,
    "total_events": 1578996,
    "events_after_PID_Cuts": 901636,
    "Pass_1_PID_Cut_events": 1097597,
    "Multiple_Pions_Per_event": 201624,
    "RunTime_in_secs": 4266,
    "timestamp": "2026-04-17T09:55:16.892569824Z"
  },
  "File: Charge_Summary_Data_sidis_epip_richcap.inb.qa.new8.nSidis_005393.hipo.json": {
    "input_file": "nSidis_005393.hipo",
    "output_root": "Data_sidis_epip_richcap.inb.qa.new8.nSidis_005393.hipo.root",
    "accumulated_charge": 364419.20505399996,
    "total_events": 2890988,
    "events_after_PID_Cuts": 1651890,
    "Pass_1_PID_Cut_events": 2010797,
    "Multiple_Pions_Per_event": 367901,
    "RunTime_in_secs": 7675,
    "timestamp": "2026-04-17T10:58:14.912682723Z"
  },
  "File: Charge_Summary_Data_sidis_epip_richcap.inb.qa.new8.nSidis_005398.hipo.json": {
    "input_file": "nSidis_005398.hipo",
    "output_root": "Data_sidis_epip_richcap.inb.qa.new8.nSidis_005398.hipo.root",
    "accumulated_charge": 40712.33513,
    "total_events": 324234,
    "events_after_PID_Cuts": 184360,
    "Pass_1_PID_Cut_events": 224810,
    "Multiple_Pions_Per_event": 41602,
    "RunTime_in_secs": 898,
    "timestamp": "2026-04-17T09:14:29.319122659Z"
  },
  "File: Charge_Summary_Data_sidis_epip_richcap.inb.qa.new8.nSidis_005400.hipo.json": {
    "input_file": "nSidis_005400.hipo",
    "output_root": "Data_sidis_epip_richcap.inb.qa.new8.nSidis_005400.hipo.root",
    "accumulated_charge": 33997.25759,
    "total_events": 268394,
    "events_after_PID_Cuts": 152487,
    "Pass_1_PID_Cut_events": 186037,
    "Multiple_Pions_Per_event": 34084,
    "RunTime_in_secs": 759,
    "timestamp": "2026-04-17T09:27:12.108630650Z"
  },
  "File: Charge_Summary_Data_sidis_epip_richcap.inb.qa.new8.nSidis_005401.hipo.json": {
    "input_file": "nSidis_005401.hipo",
    "output_root": "Data_sidis_epip_richcap.inb.qa.new8.nSidis_005401.hipo.root",
    "accumulated_charge": 31997.853020000002,
    "total_events": 254842,
    "events_after_PID_Cuts": 145500,
    "Pass_1_PID_Cut_events": 176974,
    "Multiple_Pions_Per_event": 32911,
    "RunTime_in_secs": 710,
    "timestamp": "2026-04-17T09:36:12.184791775Z"
  },
  "File: Charge_Summary_Data_sidis_epip_richcap.inb.qa.new8.nSidis_005402.hipo.json": {
    "input_file": "nSidis_005402.hipo",
    "output_root": "Data_sidis_epip_richcap.inb.qa.new8.nSidis_005402.hipo.root",
    "accumulated_charge": 0.0,
    "total_events": 0,
    "events_after_PID_Cuts": 0,
    "Pass_1_PID_Cut_events": 0,
    "Multiple_Pions_Per_event": 0,
    "RunTime_in_secs": 17,
    "timestamp": "2026-04-17T09:27:33.885110438Z"
  },
  "File: Charge_Summary_Data_sidis_epip_richcap.inb.qa.new8.nSidis_005403.hipo.json": {
    "input_file": "nSidis_005403.hipo",
    "output_root": "Data_sidis_epip_richcap.inb.qa.new8.nSidis_005403.hipo.root",
    "accumulated_charge": 0.0,
    "total_events": 0,
    "events_after_PID_Cuts": 0,
    "Pass_1_PID_Cut_events": 0,
    "Multiple_Pions_Per_event": 0,
    "RunTime_in_secs": 25,
    "timestamp": "2026-04-17T09:27:49.986090567Z"
  },
  "File: Charge_Summary_Data_sidis_epip_richcap.inb.qa.new8.nSidis_005404.hipo.json": {
    "input_file": "nSidis_005404.hipo",
    "output_root": "Data_sidis_epip_richcap.inb.qa.new8.nSidis_005404.hipo.root",
    "accumulated_charge": 0.0,
    "total_events": 0,
    "events_after_PID_Cuts": 0,
    "Pass_1_PID_Cut_events": 0,
    "Multiple_Pions_Per_event": 0,
    "RunTime_in_secs": 10,
    "timestamp": "2026-04-17T09:27:47.527020314Z"
  },
  "File: Charge_Summary_Data_sidis_epip_richcap.inb.qa.new8.nSidis_005406.hipo.json": {
    "input_file": "nSidis_005406.hipo",
    "output_root": "Data_sidis_epip_richcap.inb.qa.new8.nSidis_005406.hipo.root",
    "accumulated_charge": 180061.04247000001,
    "total_events": 1442601,
    "events_after_PID_Cuts": 825950,
    "Pass_1_PID_Cut_events": 1004376,
    "Multiple_Pions_Per_event": 184377,
    "RunTime_in_secs": 3993,
    "timestamp": "2026-04-17T10:34:24.266426157Z"
  },
  "File: Charge_Summary_Data_sidis_epip_richcap.inb.qa.new8.nSidis_005407.hipo.json": {
    "input_file": "nSidis_005407.hipo",
    "output_root": "Data_sidis_epip_richcap.inb.qa.new8.nSidis_005407.hipo.root",
    "accumulated_charge": 416039.03369999997,
    "total_events": 3312355,
    "events_after_PID_Cuts": 1890521,
    "Pass_1_PID_Cut_events": 2300531,
    "Multiple_Pions_Per_event": 422840,
    "RunTime_in_secs": 8881,
    "timestamp": "2026-04-17T11:55:54.041971193Z"
  },
  "File: Charge_Summary_Data_sidis_epip_richcap.inb.qa.new8.nSidis_005414.hipo.json": {
    "input_file": "nSidis_005414.hipo",
    "output_root": "Data_sidis_epip_richcap.inb.qa.new8.nSidis_005414.hipo.root",
    "accumulated_charge": 0.0,
    "total_events": 0,
    "events_after_PID_Cuts": 0,
    "Pass_1_PID_Cut_events": 0,
    "Multiple_Pions_Per_event": 0,
    "RunTime_in_secs": 26,
    "timestamp": "2026-04-17T09:32:05.881776718Z"
  },
  "File: Charge_Summary_Data_sidis_epip_richcap.inb.qa.new8.nSidis_005415.hipo.json": {
    "input_file": "nSidis_005415.hipo",
    "output_root": "Data_sidis_epip_richcap.inb.qa.new8.nSidis_005415.hipo.root",
    "accumulated_charge": 0.0,
    "total_events": 0,
    "events_after_PID_Cuts": 0,
    "Pass_1_PID_Cut_events": 0,
    "Multiple_Pions_Per_event": 0,
    "RunTime_in_secs": 16,
    "timestamp": "2026-04-17T09:32:25.955495663Z"
  },
  "File: Charge_Summary_Data_sidis_epip_richcap.inb.qa.new8.nSidis_005416.hipo.json": {
    "input_file": "nSidis_005416.hipo",
    "output_root": "Data_sidis_epip_richcap.inb.qa.new8.nSidis_005416.hipo.root",
    "accumulated_charge": 0.0,
    "total_events": 0,
    "events_after_PID_Cuts": 0,
    "Pass_1_PID_Cut_events": 0,
    "Multiple_Pions_Per_event": 0,
    "RunTime_in_secs": 33,
    "timestamp": "2026-04-17T09:33:02.413223916Z"
  },
  "File: Charge_Summary_Data_sidis_epip_richcap.inb.qa.new8.nSidis_005417.hipo.json": {
    "input_file": "nSidis_005417.hipo",
    "output_root": "Data_sidis_epip_richcap.inb.qa.new8.nSidis_005417.hipo.root",
    "accumulated_charge": 0.0,
    "total_events": 0,
    "events_after_PID_Cuts": 0,
    "Pass_1_PID_Cut_events": 0,
    "Multiple_Pions_Per_event": 0,
    "RunTime_in_secs": 34,
    "timestamp": "2026-04-17T09:33:39.659863609Z"
  },
  "File: Charge_Summary_Data_sidis_epip_richcap.inb.qa.new8.nSidis_005418.hipo.json": {
    "input_file": "nSidis_005418.hipo",
    "output_root": "Data_sidis_epip_richcap.inb.qa.new8.nSidis_005418.hipo.root",
    "accumulated_charge": 0.0,
    "total_events": 0,
    "events_after_PID_Cuts": 0,
    "Pass_1_PID_Cut_events": 0,
    "Multiple_Pions_Per_event": 0,
    "RunTime_in_secs": 19,
    "timestamp": "2026-04-17T09:34:03.074465688Z"
  },
  "File: Charge_Summary_Data_sidis_epip_richcap.inb.qa.new8.nSidis_005419.hipo.json": {
    "input_file": "nSidis_005419.hipo",
    "output_root": "Data_sidis_epip_richcap.inb.qa.new8.nSidis_005419.hipo.root",
    "accumulated_charge": 0.0,
    "total_events": 0,
    "events_after_PID_Cuts": 0,
    "Pass_1_PID_Cut_events": 0,
    "Multiple_Pions_Per_event": 0,
    "RunTime_in_secs": 18,
    "timestamp": "2026-04-17T09:34:24.776798251Z"
  },
  "Final_Totals": {
    "Date_Compiled": "Ran on 4-22-2026 at 06:54 p.m.",
    "Total_Number_of_Files": 171,
    "Total_accumulated_charge": 35023407.601823784,
    "Total_events": 283725048,
    "Total_events_after_PID_Cuts": 163863420,
    "Total_Pass_1_PID_Cut_events": 198638581,
    "Total_Multiple_Pions_Per_event": 36493757,
    "Average_Runtime": "5315.7310 seconds (1.4766 hours)"
  }
}